Workbook

Sheet Overall - Top sheet
A1: QUEEN MIRA INTERNATIONAL SCHOOL
A2: TOP SHEET - SALARY STATEMENT JUNE 2026
A3: S. No | B3: Particulars | C3: No of Employees | D3: Gross Salary ( A ) | E3: Average Salary | F3: Deductions | L3: Net Salary [D] | M3: Employer Contribution | O3: Total [A+E+F]
F4: Late / Permission / Leave / Absent LOP | G4: Not Punched LOP | H4: Salary Advance / Loan | I4: Special Deductions [Telephone Bill + Laptop + Uniform + Trainings etc] | J4: PF 12% [B] | K4: ESI 0.75% [C] | M4: PF 13.01% [E] | N4: ESI 3.25% [F]
A5: 1 | B5: Academics Staff | C5: =Academics!#REF! -> #REF! | D5: =Academics!V7+Academics!X7 -> 172000 | E5: =D5/C5 -> #REF! | F5: =Academics!AB7 -> 0 | G5: =Academics!AD7 -> 0 | H5: =Academics!AE7 -> 12500 | I5: =Academics!AF7 -> 13799 | J5: =Academics!AG7 -> 1800 | K5: =Academics!AH7 -> 0 | L5: =Academics!AJ7 -> 102700 | M5: =Academics!AK7 -> 1951.5 | N5: =Academics!AL7 -> 0 | O5: =D5+M5+N5 -> 173951.5
A6: 2 | B6: Admin Staff | C6: =Admin!#REF! -> #REF! | D6: =Admin!V7+Admin!X7 -> 125000 | E6: =D6/C6 -> #REF! | F6: =Admin!AB7 -> 0 | G6: =Admin!AD7 -> 0 | H6: =Admin!AE7 -> 10000 | I6: =Admin!AF7 -> 21000 | J6: =Admin!AG7 -> 1800 | K6: =Admin!AH7 -> 0 | L6: =Admin!AJ7 -> 92200 | M6: =Admin!AK7 -> 1951.5 | N6: =Admin!AL7 -> 0 | O6: =D6+M6+N6 -> 126951.5
A7: 3 | B7: Drivers | C7: ='Relieved Admin'!#REF! -> #REF! | D7: =Drivers!V7 -> 46400 | E7: =D7/C7 -> #REF! | F7: =Drivers!AB7 -> 0 | G7: =Drivers!AD7 -> 0 | H7: =Drivers!AE7 -> 0 | I7: =Drivers!AF7 -> 2500 | J7: =Drivers!AG7 -> 2506 | K7: =Drivers!AH7 -> 172 | L7: =Drivers!AJ7 -> 41222 | M7: =Drivers!AK7 -> 2717 | N7: =Drivers!AL7 -> 745 | O7: =D7+M7+N7 -> 49862
A8: 4 | B8: Conductors | C8: =+Conductors!#REF! -> #REF! | D8: =Conductors!W7+Conductors!X7 -> 22300 | E8: =D8/C8 -> #REF! | F8: =Conductors!AB7 -> 0 | G8: =Conductors!AD7 -> 0 | H8: =Conductors!AE7 -> 0 | I8: =Conductors!AF7 -> 0 | J8: =Conductors!AG7 -> 697 | K8: =Conductors!AH7 -> 97 | L8: =Conductors!AJ7 -> 21506 | M8: =Conductors!AK7 -> 756 | N8: =Conductors!AL7 -> 420 | O8: =D8+M8+N8 -> 23476
A9: 5 | B9: Securities | C9: =Securities!#REF! -> #REF! | D9: =Securities!V7+Securities!X7 -> 44300 | E9: =D9/C9 -> #REF! | F9: =Securities!AB7 -> 416.66667 | G9: =Securities!AD7 -> 0 | H9: =Securities!AE7 -> 10000 | I9: =Securities!AF7 -> 0 | J9: =Securities!AG7 -> 0 | K9: =Securities!AH7 -> 0 | L9: =Securities!AJ7 -> 33883 | M9: =Securities!AK7 -> 0 | N9: =Securities!AL7 -> 0 | O9: =D9+M9+N9 -> 44300
A10: 6 | B10: Housekeeping | C10: =+'House Keeping'!#REF! -> #REF! | D10: ='House Keeping'!V7 -> 27800 | E10: =D10/C10 -> #REF! | F10: ='House Keeping'!AB7 -> 0 | G10: ='House Keeping'!AD7 -> 0 | H10: ='House Keeping'!AE7 -> 2000 | I10: ='House Keeping'!AF7 -> 0 | J10: ='House Keeping'!AG7 -> 1502 | K10: ='House Keeping'!AH7 -> 210 | L10: ='House Keeping'!AJ7 -> 24088 | M10: ='House Keeping'!AK7 -> 1629 | N10: ='House Keeping'!AL7 -> 904 | O10: =D10+M10+N10 -> 30333
A11: 7 | B11: Hostel | C11: =Hostel!A7 -> 3 | D11: =Hostel!V8 -> 40500 | E11: =D11/C11 -> 13500 | F11: =Hostel!AB8 -> 0 | G11: =Hostel!AD8 -> 0 | H11: =Hostel!AE8 -> 0 | I11: =Hostel!AF8 -> 0 | J11: =Hostel!AG8 -> 0 | K11: =Hostel!AH8 -> 0 | L11: =Hostel!AJ8 -> 40500 | M11: =Hostel!AK8 -> 0 | N11: =Hostel!AL8 -> 0 | O11: =D11+M11+N11 -> 40500
A12: 8 | B12: ECA | C12: =+'ECA '!A18 -> 14 | D12: =+'ECA '!D19 -> 221000 | E12: =D12/C12 -> 15785.714 | F12: =+'ECA '!K19 -> 4449.5968 | G12: 0 | H12: =+'ECA '!J19 -> 0 | I12: =+'ECA '!H19 -> 0 | J12: 0 | K12: 0 | L12: =+'ECA '!M19 -> 216551 | M12: 0 | N12: 0 | O12: =D12+M12+N12 -> 221000
A13: 9 | B13: Part Time - Academics | C13: =+'Part time academic'!A12 -> 11 | D13: =+'Part time academic'!D14 -> 286558.67 | E13: =D13/C13 -> 26050.788 | F13: =+'Part time academic'!I14 -> 666.66667 | G13: 0 | H13: 0 | I13: =+'Part time academic'!H14 -> 0 | J13: 0 | K13: 0 | L13: =+'Part time academic'!J14 -> 279225 | M13: 0 | N13: 0 | O13: =D13+M13+N13 -> 286558.67
A14: 10 | B14: Theni Upparpatti | C14: =+'Theni - Upparpatti'!#REF! -> #REF! | D14: ='Theni - Upparpatti'!V7 -> 20000 | E14: =D14/C14 -> #REF! | F14: ='Theni - Upparpatti'!AB7 -> 0 | G14: ='Theni - Upparpatti'!AD7 -> 0 | H14: ='Theni - Upparpatti'!AE7 -> 0 | I14: ='Theni - Upparpatti'!AF7 -> 0 | J14: ='Theni - Upparpatti'!AG7 -> 0 | K14: ='Theni - Upparpatti'!AH7 -> 0 | L14: ='Theni - Upparpatti'!AJ7 -> 20000 | M14: ='Theni - Upparpatti'!AK7 -> 0 | N14: ='Theni - Upparpatti'!AL7 -> 0 | O14: =D14+M14+N14 -> 20000
A15: 11 | B15: Academic Enrichment Program | C15: =+AEP!#REF! -> #REF! | D15: =+AEP!D6 -> 0 | E15: =D15/C15 -> #REF! | F15: =AEP!G6 -> 0 | I15: =AEP!F6 -> 0 | L15: =AEP!I6 -> 0 | O15: =D15+M15+N15 -> 0
A16: 12 | B16: Rifle Shooting | C16: =Rifle!A4 -> 1 | D16: =Rifle!D5 -> 66000 | E16: =D16/C16 -> 66000 | F16: =Rifle!J5 -> 0 | H16: =Rifle!H5 -> 0 | I16: =Rifle!F5 -> 0 | L16: =Rifle!L5 -> 66000 | O16: =D16+M16+N16 -> 66000
A17: 13 | B17: Part Time Admin | C17: ='Part Time - Admin'!A5 -> 2 | D17: ='Part Time - Admin'!D6 -> 35000 | E17: =D17/C17 -> 17500 | F17: ='Part Time - Admin'!L6 -> 0 | H17: 0 | I17: ='Part Time - Admin'!K6 -> 0 | L17: ='Part Time - Admin'!N6 -> 35000 | O17: =D17+M17+N17 -> 35000
A18: 14 | B18: Relieved Academics | C18: ='Relieved Academics'!A6 -> 2 | D18: ='Relieved Academics'!V7 -> 90000 | E18: 0 | F18: ='Relieved Academics'!AB7 -> 3000 | G18: ='Relieved Academics'!AD7 -> 0 | H18: ='Relieved Academics'!AE7 -> 0 | I18: ='Relieved Academics'!AF7 -> 4172 | J18: ='Relieved Academics'!AG7 -> 0 | K18: ='Relieved Academics'!AH7 -> 0 | L18: ='Relieved Academics'!AJ8 -> 46828 | M18: ='Relieved Academics'!AK7 -> 0 | N18: ='Relieved Academics'!AL7 -> 0 | O18: =D18+M18+N18 -> 90000
A19: 15 | B19: Relieved Admin | C19: ='Relieved Admin'!#REF! -> #REF! | D19: ='Relieved Admin'!V7 -> 34000 | E19: 0 | F19: ='Relieved Admin'!AB7 -> 0 | G19: ='Relieved Admin'!E7 -> 0 | H19: ='Relieved Admin'!AE7 -> 0 | I19: ='Relieved Admin'!AF7 -> 0 | J19: ='Relieved Admin'!AG7 -> 0 | K19: ='Relieved Admin'!AH7 -> 0 | L19: ='Relieved Admin'!AJ8 -> 9467 | M19: ='Relieved Admin'!AK7 -> 0 | N19: ='Relieved Admin'!AL7 -> 0 | O19: =D19+M19+N19 -> 34000
A20: Total | C20: =+C5+C6+C7+C8+C9+C10+2+12+12+3+1+2 -> #REF! | D20: =SUM(D5:D19) -> 1230858.7 | E20: =SUM(E5:E19) -> #REF! | F20: =SUM(F5:F19) -> 8532.9301 | G20: =SUM(G5:G19) -> 0 | H20: =SUM(H5:H19) -> 34500 | I20: =SUM(I5:I19) -> 41471 | J20: =SUM(J5:J19) -> 8305 | K20: =SUM(K5:K19) -> 479 | ... O20: =SUM(O5:O19) -> 1241932.7
A22: Payable Total (B+C+D+E+F) | O22: =J20+K20+L20+M20+N20 -> 1049028
A23: HR Manager | C23: Finance Manager | F23: Joint Director Admin | J23: Director Academics | N23: Managing Director

Sheet Academics
A1: QUEEN MIRA INTERNATIONAL SCHOOL
A2: ACADEMICS - SALARY STATEMENT JUNE 2026
A3: S.No | B3: Name | C3: Department | D3: Attendance | R3: Salary Advance / Loan Details | V3: Gross Salary | W3: Payable Gross Salary | X3: Other Allownace | Y3: Salary.Actuals [Gross Salary - Leave Deduction] | Z3: Salary per day [Gross salary / no of days that month] | AA3: Basic [45% of Gross Salary] | AB3: Deductions | AJ3: Net Salary | AK3: QMIS Contribution | AM3: Remarks
D4: Total working days | E4: Lates. Actuals | F4: Lates. Leave [Exceeding lates conversions count] | G4: Final Lates after deducting exceeding Late leaves | H4: Permissions.Actuals | I4: Exceeding Permissions taken for this month | J4: Proper Permissions | K4: Proper Casual Leave already taken for this year till date | L4: Proper Casual Leave taken for this month | M4: Exceeding Casual Leave taken for this month / Memo issued | N4: Absent / Suspension.Actuals | O4: Gardening / Other Leave | P4: Total Leave days.Actuals | Q4: Loss of Pay Days | R4: Total Loan Amount | S4: Amount already paid | T4: Amount to be paid for this month | U4: Remaining Loan Amount | AB4: Leave / Absent / Permission Leave / Late Leave | AC4: Not Punched Days | AD4: Not Punched LOP | AE4: Salary Advance / Loan | AF4: Special Deductions [Telephone Bill + healthcheck up + Uniform + Trainings etc] | AG4: PF [12% of Basic Salary] | AH4: ESI [0.75% of Salary.Actuals] | AI4: Total | AK4: PF [13.01% of Basic Salary] | AL4: ESI [3.25% of Salary.Actuals]
A5: 1 | B5: SUJATHA D/O SUBBURAM | C5: Director - Academics | D5: 30 | E5: 0 | F5: =IF((E5/3)>=1,TRUNC(E5/3,0),0) -> 0 | G5: =E5-F5*3 -> 0 | H5: 0 | I5: =IF(H5<1,H5,H5-1) -> 0 | J5: =H5-I5 -> 0 | K5: 0 | L5: 1.5 | M5: 0 | N5: 0 | O5: 0 | P5: =L5+M5+N5+O5 -> 1.5 | Q5: =(F5*0.5)+(I5*0.5)+M5+(N5*2) -> 0 | R5: =125000 -> 125000 | S5: =12500+12500+12500 -> 37500 | T5: 12500 | U5: =R5-(S5+T5) -> 75000 | V5: 130000 | W5: =V5 -> 130000 | X5: 0 | Y5: =W5-AB5 -> 130000 | Z5: =V5/D5 -> 4333.3333 | AA5: 15000 | AB5: =Q5*Z5 -> 0 | AD5: =(AC5)*Z5 -> 0 | AE5: =T5 -> 12500 | AF5: =2500+10000+500 -> 13000 | AG5: =(AA5*12%) -> 1800 | AH5: 0 | AI5: =SUM(AB5,AD5:AH5) -> 27300 | AJ5: =ROUND(SUM(W5:X5)-AI5,0) -> 102700 | AK5: =(AA5*13.01%) -> 1951.5 | AL5: 0 | AM5: Chit 4th month. Salary Adv Note: 4 Pg No: 36. | AN5: 1750155000050628
A6: 2 | B6: A JAINCOL FATHIMA | C6: Assistant Vice Principal Kinder Garten / PRT-English | D6: 30 | E6: 0 | F6: =IF((E6/3)>=1,TRUNC(E6/3,0),0) -> 0 | G6: =E6-F6*3 -> 0 | H6: 0 | I6: =IF(H6<1,H6,H6-1) -> 0 | J6: =H6-I6 -> 0 | K6: 0 | M6: 0 | N6: 0 | O6: 0 | P6: =L6+M6+N6+O6 -> 0 | Q6: =(F6*0.5)+(I6*0.5)+M6+(N6*2) -> 0 | R6: 0 | S6: 0 | T6: 0 | U6: =R6-(S6+T6) -> 0 | V6: 42000 | W6: =V6 -> 42000 | X6: 0 | Y6: =W6-AB6 -> 42000 | Z6: =V6/D6 -> 1400 | AA6: =W6*45% -> 18900 | AB6: =Q6*Z6 -> 0 | AC6: 0 | AD6: =(AC6)*Z6 -> 0 | AE6: =T6 -> 0 | AF6: =299+500 -> 799 | AG6: 0 | AH6: 0 | AI6: =SUM(AB6,AD6:AH6) -> 799 | AK6: 0 | AL6: 0 | AN6: 1750061000000064
R7: =SUM(R5:R6) -> 125000 | S7: =SUM(S5:S6) -> 37500 | T7: =SUM(T5:T6) -> 12500 | U7: =SUM(U5:U6) -> 75000 | V7: =SUM(V5:V6) -> 172000 | W7: =SUM(W5:W6) -> 172000 | X7: =SUM(X5:X6) -> 0 | Y7: =SUM(Y5:Y6) -> 172000 | ... AM7: =SUM(AM5:AM6) -> 0
A8: Note : An amount of ₹500 has already been deducted from your salary towards the Staff Planner Kit
A9: HR Manager | W9: Finance Manager | AL9: Director Academics

Sheet Relieved Academics
A1: QUEEN MIRA INTERNATIONAL SCHOOL
A2: ACADEMICS RELIEVED- SALARY STATEMENT JUNE 2026
A3: S.No | B3: Name | C3: Department | D3: Attendance | R3: Salary Advance / Loan Details | V3: Gross Salary | W3: Payable Gross Salary | X3: Other Allowance | Y3: Salary. Actuals [Gross Salary - Leave Deduction] | Z3: Salary per day [Gross salary / no of days that month] | AA3: Basic [45% of Gross Salary] | AB3: Deductions | AJ3: Net Salary | AK3: QMIS Contribution | AM3: Remarks
D4: Total working days | E4: Lates. Actuals | F4: Lates. Leave [Exceeding lates conversions count] | G4: Final Lates after deducting exceeding Late leaves | H4: Permissions. Actuals | I4: Exceeding Permissions taken for this month | J4: Proper Permissions | K4: Proper Casual Leave already taken for this year till date | L4: Proper Casual Leave taken for this month | M4: Exceeding Casual Leave taken for this month | N4: Absent / Suspension. Actuals | O4: Gardening / Other Leave | P4: Total Leave days. Actuals | Q4: Loss of Pay Days | R4: Total Loan Amount | S4: Amount already paid | T4: Amount to be paid for this month | U4: Remaining Loan Amount | AB4: Leave / Absent / Permission Leave / Late Leave | AC4: Not Punched Days | AD4: Not Punched LOP | AE4: Salary Advance / Loan | AF4: Special Deductions [Telephone Bill + Laptop + Uniform + Trainings etc] | AG4: PF [12% of Basic Salary] | AH4: ESI [0.75% of Salary. Actuals] | AI4: Total | AK4: PF [13.01% of Basic Salary] | AL4: ESI [3.25% of Salary. Actuals]
A5: 1 | B5: Rajasekar | C5: AEP Coordinator / Mentor Grade 9 to 12 | D5: 12 | E5: 0 | F5: =IF((E5/3)>=1,TRUNC(E5/3,0),0) -> 0 | G5: =E5-F5*3 -> 0 | H5: 0 | I5: =IF(H5<1,H5,H5-1) -> 0 | J5: =H5-I5 -> 0 | K5: 0 | L5: 1 | M5: 1.5 | N5: 0 | O5: 0 | P5: =L5+M5+N5+O5 -> 2.5 | Q5: =(F5*0.5)+(I5*0.5)+M5+(N5*2) -> 1.5 | U5: =R5-(S5+T5) -> 0 | V5: 60000 | W5: =V5/30*12 -> 24000 | Y5: =W5-AB5 -> 21000 | Z5: =V5/30 -> 2000 | AA5: =W5*45% -> 10800 | AB5: =Q5*Z5 -> 3000 | AD5: =(AC5)*Z5 -> 0 | AE5: =T5 -> 0 | AG5: 0 | AH5: 0 | AI5: =SUM(AB5,AD5:AH5) -> 3000 | AJ5: =ROUND(SUM(W5:X5)-AI5,0) -> 21000 | AM5: As per MD's Intrcution Lates Not Considered. Relieved on 12/06/2026 | AN5: 1750060000003764
A6: 2 | B6: R Veerachinna Krishnan | C6: TGT - Hindi | D6: 30 | E6: 1 | F6: =IF((E6/3)>=1,TRUNC(E6/3,0),0) -> 0 | G6: =E6-F6*3 -> 1 | H6: 0 | I6: =IF(H6<1,H6,H6-1) -> 0 | J6: =H6-I6 -> 0 | K6: 0 | L6: 2 | M6: 0 | N6: 0 | O6: 0 | P6: =L6+M6+N6+O6 -> 2 | Q6: =(F6*0.5)+(I6*0.5)+M6+(N6*2) -> 0 | U6: =R6-(S6+T6) -> 0 | V6: 30000 | W6: =V6 -> 30000 | Y6: =W6-AB6 -> 30000 | Z6: =V6/D6 -> 1000 | AA6: =W6*45% -> 13500 | AB6: =Q6*Z6 -> 0 | AD6: =(AC6)*Z6 -> 0 | AE6: =T6 -> 0 | AF6: =1043*4 -> 4172 | AG6: 0 | AH6: 0 | AI6: =SUM(AB6,AD6:AH6) -> 4172 | AJ6: =ROUND(SUM(W6:X6)-AI6,0) -> 25828 | AM6: Uniform 2/6 deduction. Relieved on 30.06.2026 .Uniform Full amount deducted | AN6: 1750060000003788
A7: TOTAL | R7: =SUM(R5:R6) -> 0 | S7: =SUM(S5:S6) -> 0 | T7: =SUM(T5:T6) -> 0 | U7: =SUM(U5:U6) -> 0 | V7: =SUM(V5:V6) -> 90000 | W7: =SUM(W5:W6) -> 54000 | X7: =SUM(X5:X6) -> 0 | Y7: =SUM(Y5:Y6) -> 51000 | ... AL7: =SUM(AL5:AL6) -> 0
AD8: Payable salary | AJ8: =+AJ7 -> 46828
A9: HR Manager | U9: Finance Manager | AK9: Director Academics

Sheet Admin
A1: QUEEN MIRA INTERNATIONAL SCHOOL
A2: ADMIN - SALARY STATEMENT JUNE 2026
A3: S.No | B3: Name | C3: Department | D3: Attendance | R3: Salary Advance / Loan Details | V3: Gross Salary | W3: Payable Gross Salary | X3: Other Allownace | Y3: Salary.Actuals [Gross Salary - Leave Deduction] | Z3: Salary per day [Gross salary / no of days that month] | AA3: Basic [45% of Gross Salary] | AB3: Deductions | AJ3: Net Salary | AK3: QMIS Contribution | AM3: Remarks
D4: Total working days | E4: Lates. Actuals | F4: Lates. Leave [Exceeding lates conversions count] | G4: Final Lates after deducting exceeding Late leaves | H4: Permissions.Actuals | I4: Exceeding Permissions taken for this month | J4: Proper Permissions | K4: Proper Casual Leave already taken for this year till date | L4: Proper Casual Leave taken for this month | M4: Exceeding Casual Leave taken for this month / Memo issued | N4: Absent / Suspension.Actuals | O4: Gardening / Other Leave | P4: Total Leave days.Actuals | Q4: Loss of Pay Days | R4: Total Loan Amount | S4: Amount already paid | T4: Amount to be paid for this month | U4: Remaining Loan Amount | AB4: Leave / Absent / Permission Leave / Late Leave | AC4: Not Punched Days | AD4: Not Punched LOP | AE4: Salary Advance / Loan | AF4: Special Deductions [Telephone Bill + healthcheck up + Uniform + Trainings etc] | AG4: PF [12% of Basic Salary] | AH4: ESI [0.75% of Salary.Actuals] | AI4: Total | AK4: PF [13.01% of Basic Salary] | AL4: ESI [3.25% of Salary.Actuals]
A5: 1 | B5: JOSEPHINE ANNE SHEEBHA ARULDASS | C5: Joint Director- Admin | D5: 30 | E5: 0 | F5: =IF((E5/3)>=1,TRUNC(E5/3,0),0) -> 0 | G5: =E5-F5*3 -> 0 | H5: 0 | I5: =IF(H5<1,H5,H5-1) -> 0 | J5: =H5-I5 -> 0 | K5: 0 | L5: 0.5 | M5: 0 | N5: 0 | O5: 0 | P5: =L5+M5+N5+O5 -> 0.5 | Q5: =(F5*0.5)+(I5*0.5)+M5+(N5*2) -> 0 | R5: =100000+100000+50000 -> 250000 | S5: =10000+10000+10000+10000+10000+10000+10000+10000+10000+10000+10000 -> 110000 | T5: 10000 | U5: =R5-(S5+T5) -> 130000 | V5: 100000 | W5: =V5 -> 100000 | X5: 0 | Y5: =W5-AB5 -> 100000 | Z5: =V5/D5 -> 3333.3333 | AA5: 15000 | AB5: =Q5*Z5 -> 0 | AD5: =(AC5)*Z5 -> 0 | AE5: =T5 -> 10000 | AF5: =10000+10000+500 -> 20500 | AG5: =(AA5*12%) -> 1800 | AH5: 0 | AI5: =SUM(AB5,AD5:AH5) -> 32300 | AJ5: =ROUND(SUM(W5:X5)-AI5,0) -> 67700 | AK5: =(AA5*13.01%) -> 1951.5 | AL5: 0 | AM5: 5,000 will be given as cash. Salary Adv Note :4 Pg No. 19. Chit 4th month | AN5: 1750062000000072
A6: 2 | B6: Jeya Dharini Abinath | C6: GM - Finance | D6: 30 | E6: 0 | F6: =IF((E6/3)>=1,TRUNC(E6/3,0),0) -> 0 | G6: =E6-F6*3 -> 0 | H6: 0 | I6: =IF(H6<1,H6,H6-1) -> 0 | J6: =H6-I6 -> 0 | K6: 0 | L6: 0 | M6: 0 | N6: 0 | O6: 0 | P6: =L6+M6+N6+O6 -> 0 | Q6: =(F6*0.5)+(I6*0.5)+M6+(N6*2) -> 0 | U6: =R6-(S6+T6) -> 0 | V6: 25000 | W6: =V6 -> 25000 | X6: 0 | Y6: =W6-AB6 -> 25000 | Z6: =V6/D6 -> 833.33333 | AA6: =W6*45% -> 11250 | AB6: =Q6*Z6 -> 0 | AD6: =(AC6)*Z6 -> 0 | AE6: =T6 -> 0 | AF6: 500 | AG6: 0 | AH6: 0 | AI6: =SUM(AB6,AD6:AH6) -> 500 | AJ6: =ROUND(SUM(W6:X6)-AI6,0) -> 24500 | AK6: 0 | AL6: 0
R7: =SUM(R5:R6) -> 250000 | S7: =SUM(S5:S6) -> 110000 | T7: =SUM(T5:T6) -> 10000 | U7: =SUM(U5:U6) -> 130000 | V7: =SUM(V5:V6) -> 125000 | W7: =SUM(W5:W6) -> 125000 | X7: =SUM(X5:X6) -> 0 | Y7: =SUM(Y5:Y6) -> 125000 | ... AL7: =SUM(AL5:AL6) -> 0
A8: Note : An amount of ₹500 has already been deducted from your salary towards the Staff Planner Kit
A9: HR Manager | W9: Finance Manager | AL9: Joint Director - Admin
G15: =43-15 -> 28

Sheet Relieved Admin
A1: QUEEN MIRA INTERNATIONAL SCHOOL
A2: ADMIN RELIEVED - SALARY STATEMENT JUNE 2026
A3: S.No | B3: Name | C3: Department | D3: Attendance | R3: Salary Advance / Loan Details | V3: Gross Salalry | W3: Payable Gross Salary | X3: Other Allownace | Y3: Salary.Actuals [Gross Salary - Leave Deduction] | Z3: Salary per day [Gross salary / no of days that month] | AA3: Basic [45% of Gross Salary] | AB3: Deductions | AJ3: Net Salary | AK3: QMIS Contribution | AM3: Remarks
D4: Total working days | E4: Lates. Actuals | F4: Lates. Leave [Exceeding lates conversions count] | G4: Final Lates after deducting exceeding Late leaves | H4: Permissions.Actuals | I4: Exceeding Permissions taken for this month | J4: Proper Permissions | K4: Proper Casual Leave already taken for this year till date | L4: Proper Casual Leave taken for this month | M4: Exceeding Casual Leave taken for this month | N4: Absent / Suspension.Actuals | O4: Gardening / Other Leave | P4: Total Leave days.Actuals | Q4: Loss of Pay Days | R4: Total Loan Amount | S4: Amount already paid | T4: Amount to be paid for this month | U4: Remaining Loan Amount | AB4: Leave / Absent / Permission Leave / Late Leave | AC4: Not Punched Days | AD4: Not Punched LOP | AE4: Salary Advance / Loan | AF4: Special Deductions [Telephone Bill + Laptop + Uniform + Trainings etc] | AG4: PF [12% of Basic Salary] | AH4: ESI [0.75% of Salary.Actuals] | AI4: Total | AK4: PF [13.01% of Basic Salary] | AL4: ESI [3.25% of Salary.Actuals]
A5: 1 | B5: DEEPIKA KANNAN | C5: Accountant | D5: 10 | E5: 0 | F5: =IF((E5/3)>=1,TRUNC(E5/3,0),0) -> 0 | G5: =E5-F5*3 -> 0 | H5: 0 | I5: =IF(H5<1,H5,H5-1) -> 0 | J5: =H5-I5 -> 0 | K5: 0 | L5: 1 | M5: 0 | N5: 0 | O5: 0 | P5: =L5+M5+N5+O5 -> 1 | Q5: =(F5*0.5)+(I5*0.5)+M5+(N5*2) -> 0 | U5: =R5-(S5+T5) -> 0 | V5: 20000 | W5: =V5/30*10 -> 6666.6667 | Y5: =W5-AB5 -> 6666.6667 | Z5: =V5/30 -> 666.66667 | AA5: =W5*45% -> 3000 | AB5: =Q5*Z5 -> 0 | AD5: =(AC5)*Z5 -> 0 | AE5: =T5 -> 0 | AG5: 0 | AH5: 0 | AI5: =SUM(AB5,AD5:AH5) -> 0 | AJ5: =ROUND(SUM(W5:X5)-AI5,0) -> 6667 | AK5: 0 | AL5: 0 | AM5: Relived on 10/06/2026 | AN5: 1750060000000023
A6: 2 | B6: G B Hemavathy | C6: Executive Audit | D6: 6 | E6: 0 | F6: =IF((E6/3)>=1,TRUNC(E6/3,0),0) -> 0 | G6: =E6-F6*3 -> 0 | H6: 0 | I6: =IF(H6<1,H6,H6-1) -> 0 | J6: =H6-I6 -> 0 | K6: 0 | L6: 0 | M6: 0 | N6: 0 | O6: 0 | P6: =L6+M6+N6+O6 -> 0 | Q6: =(F6*0.5)+(I6*0.5)+M6+(N6*2) -> 0 | U6: =R6-(S6+T6) -> 0 | V6: 14000 | W6: =V6/30*6 -> 2800 | X6: 0 | Y6: =W6-AB6 -> 2800 | Z6: =V6/30 -> 466.66667 | AA6: =W6*45% -> 1260 | AB6: =Q6*Z6 -> 0 | AD6: =(AC6)*Z6 -> 0 | AE6: =T6 -> 0 | AF6: 0 | AG6: 0 | AH6: 0 | AI6: =SUM(AB6,AD6:AH6) -> 0 | AJ6: =ROUND(SUM(W6:X6)-AI6,0) -> 2800 | AN6: 1750061000000572
A7: TOTAL | R7: =SUM(R5:R6) -> 0 | S7: =SUM(S5:S6) -> 0 | T7: =SUM(T5:T6) -> 0 | U7: =SUM(U5:U6) -> 0 | V7: =SUM(V5:V6) -> 34000 | W7: =SUM(W5:W6) -> 9466.6667 | X7: =SUM(X5:X6) -> 0 | Y7: =SUM(Y5:Y6) -> 9466.6667 | ... AL7: =SUM(AL5:AL6) -> 0
AD8: Payable salary | AJ8: =+AJ7 -> 9467
A9: HR Manager | U9: Finance Manager | AK9: Joint Director-Admin

Sheet Drivers
A1: QUEEN MIRA INTERNATIONAL SCHOOL
A2: DRIVERS - SALARY STATEMENT JUNE 2026
A3: S.No | B3: Name | C3: Department | D3: Attendance | R3: Salary Advance / Loan Details | V3: Gross Salary | W3: Payable Gross Salary | X3: Other Allownace | Y3: Salary.Actuals [Gross Salary - Leave Deduction] | Z3: Salary per day [Gross salary / no of days that month] | AA3: Basic [45% of Payable Gross Salary] | AB3: Deductions | AJ3: Net Salary | AK3: QMIS Contribution | AM3: Remarks
D4: Total working days | E4: Lates. Actuals | F4: Lates. Leave [Exceeding lates conversions count] | G4: Final Lates after deducting exceeding Late leaves | H4: Permissions.Actuals | I4: Exceeding Permissions taken for this month | J4: Proper Permissions | K4: Proper Casual Leave already taken for this year till date | L4: Proper Casual Leave taken for this month | M4: Exceeding Casual Leave taken for this month / Memo issued | N4: Absent / Suspension.Actuals | O4: Gardening / Other Leave | P4: Total Leave days.Actuals | Q4: Loss of Pay Days | R4: Total Loan Amount | S4: Amount already paid | T4: Amount to be paid for this month | U4: Remaining Loan Amount | AB4: Leave / Absent / Permission Leave / Late Leave | AC4: Not Punched Days | AD4: Not Punched LOP | AE4: Salary Advance / Loan | AF4: Special Deductions [Telephone Bill + healthcheck up + Uniform + Trainings etc] | AG4: PF [12% of Basic Salary] | AH4: ESI [0.75% of Salary.Actuals] | AI4: Total | AK4: PF [13.01% of Basic Salary] | AL4: ESI [3.25% of Salary.Actuals]
A5: 1 | B5: KUMARAVEL MOOKKAIAH | C5: Transport Driver | D5: 30 | E5: 0 | F5: =IF((E5/3)>=1,TRUNC(E5/3,0),0) -> 0 | G5: =E5-F5*3 -> 0 | H5: 0 | I5: =IF(H5<2,H5,H5-2) -> 0 | J5: =H5-I5 -> 0 | K5: 0 | L5: 1.5 | M5: 0 | N5: 0 | O5: 0 | P5: =L5+M5+N5+O5 -> 1.5 | Q5: =(F5*0.5)+(I5*0.5)+M5+(N5*2) -> 0 | U5: =R5-(S5+T5) -> 0 | V5: 23500 | W5: =V5 -> 23500 | X5: 0 | Y5: =(W5+X5)-AB5 -> 23500 | Z5: =(W5+X5)/D5 -> 783.33333 | AA5: =W5*45% -> 10575 | AB5: =Q5*Z5 -> 0 | AD5: =(AC5)*Z5 -> 0 | AE5: =T5 -> 0 | AG5: =ROUNDUP(AA5*12%,0) -> 1269 | AH5: 0 | AI5: =SUM(AB5,AD5:AH5) -> 1269 | AJ5: =ROUND(SUM(W5:X5)-AI5,0) -> 22231 | AK5: =ROUNDUP(AA5*13.01%,0) -> 1376 | AL5: 0 | AN5: 1750060000000508
A6: 2 | B6: DURAIMURUGAN NAGARAJAN | C6: Transport Driver | D6: 30 | E6: 0 | F6: =IF((E6/3)>=1,TRUNC(E6/3,0),0) -> 0 | G6: =E6-F6*3 -> 0 | H6: 0 | I6: =IF(H6<1,H6,H6-1) -> 0 | J6: =H6-I6 -> 0 | K6: 0 | L6: 2 | M6: 0 | N6: 0 | O6: 0 | P6: =L6+M6+N6+O6 -> 2 | Q6: =(F6*0.5)+(I6*0.5)+M6+(N6*2) -> 0 | U6: =R6-(S6+T6) -> 0 | V6: 22900 | W6: =V6 -> 22900 | Y6: =(W6+X6)-AB6 -> 22900 | Z6: =(W6+X6)/D6 -> 763.33333 | AA6: =W6*45% -> 10305 | AB6: =Q6*Z6 -> 0 | AD6: =(AC6)*Z6 -> 0 | AE6: =T6 -> 0 | AF6: 2500 | AG6: =ROUNDUP(AA6*12%,0) -> 1237 | AH6: =ROUNDUP((Y6+X6)*0.75%,0) -> 172 | AI6: =SUM(AB6,AD6:AH6) -> 3909 | AJ6: =ROUND(SUM(W6:X6)-AI6,0) -> 18991 | AK6: =ROUNDUP(AA6*13.01%,0) -> 1341 | AL6: =ROUNDUP((Y6+X6)*3.25%,0) -> 745 | AM6: Chit 4th month | AN6: 1750060000000522
A7: TOTAL | R7: =SUM(R5:R6) -> 0 | S7: =SUM(S5:S6) -> 0 | T7: =SUM(T5:T6) -> 0 | U7: =SUM(U5:U6) -> 0 | V7: =SUM(V5:V6) -> 46400 | W7: =SUM(W5:W6) -> 46400 | X7: =SUM(X5:X6) -> 0 | Y7: =SUM(Y5:Y6) -> 46400 | ... AL7: =SUM(AL5:AL6) -> 745
A8: HR Manager | U8: Finance Manager | AL8: Joint Director - Admin

Sheet Conductors
A1: QUEEN MIRA INTERNATIONAL SCHOOL
A2: CONDUCTORS - SALARY STATEMENT JUNE 2026
A3: S.No | B3: Name | C3: Department | D3: Attendance | R3: Salary Advance / Loan Details | V3: Gross Salary | W3: Payable Gross Salary | X3: Other Allownace | Y3: Salary Actuals [Gross Salary - Leave Deduction] | Z3: Salary per day [Gross salary / no of days that month] | AA3: Basic [45% of Gross Salary] | AB3: Deductions | AJ3: Net Salary | AK3: QMIS Contribution | AM3: Remarks
D4: Total working days | E4: Lates. Actuals | F4: Lates. Leave [Exceeding lates conversions count] | G4: Final Lates after deducting exceeding Late leaves | H4: Permissions.Actuals | I4: Exceeding Permissions taken for this month | J4: Proper Permissions | K4: Proper Casual Leave already taken for this year till date | L4: Proper Casual Leave taken for this month | M4: Exceeding Casual Leave taken for this month / Memo issued | N4: Absent / Suspension.Actuals | O4: Gardening / Other Leave | P4: Total Leave days.Actuals | Q4: Loss of Pay Days | R4: Total Loan Amount | S4: Amount already paid | T4: Amount to be paid for this month | U4: Remaining Loan Amount | AB4: Leave / Absent / Permission Leave / Late Leave | AC4: Not Punched Days | AD4: Not Punched LOP | AE4: Salary Advance / Loan | AF4: Special Deductions [Telephone Bill + Laptop + Uniform + Trainings etc] | AG4: PF [12% of Basic Salary] | AH4: ESI [0.75% of Salary.Actuals] | AI4: Total | AK4: PF [13.01% of Basic Salary] | AL4: ESI [3.25% of Salary.Actuals]
A5: 1 | B5: SUNDARI JEYARAM | C5: Conductor | D5: 30 | E5: 0 | F5: =IF((E5/3)>=1,TRUNC(E5/3,0),0) -> 0 | G5: =E5-F5*3 -> 0 | H5: 0 | I5: =IF(H5<2,H5,H5-2) -> 0 | J5: =H5-I5 -> 0 | K5: 0 | L5: 0.5 | M5: 0 | N5: 0 | O5: 0 | P5: =L5+M5+N5+O5 -> 0.5 | Q5: =(F5*0.5)+(I5*0.5)+M5+(N5*2) -> 0 | R5: 0 | S5: 0 | T5: 0 | U5: =R5-(S5+T5) -> 0 | V5: 9400 | W5: =V5 -> 9400 | Y5: =(W5+X5)-AB5 -> 9400 | Z5: =(W5+X5)/D5 -> 313.33333 | AA5: =W5*45% -> 4230 | AB5: =Q5*Z5 -> 0 | AC5: 0 | AD5: =(AC5)*Z5 -> 0 | AE5: =T5 -> 0 | AG5: 0 | AH5: 0 | AI5: =SUM(AB5,AD5:AH5) -> 0 | AJ5: =ROUND(SUM(W5:X5)-AI5,0) -> 9400 | AK5: 0 | AL5: 0 | AN5: 1750059000000054
A6: 2 | B6: S CHITRA | C6: Conductor | D6: 30 | E6: 0 | F6: =IF((E6/3)>=1,TRUNC(E6/3,0),0) -> 0 | G6: =E6-F6*3 -> 0 | H6: 2 | I6: =IF(H6<2,H6,H6-2) -> 0 | J6: =H6-I6 -> 2 | K6: 0 | L6: 1 | M6: 0 | N6: 0 | O6: 0 | P6: =L6+M6+N6+O6 -> 1 | Q6: =(F6*0.5)+(I6*0.5)+M6+(N6*2) -> 0 | R6: 0 | S6: 0 | T6: 0 | U6: =R6-(S6+T6) -> 0 | V6: 12900 | W6: =V6 -> 12900 | Y6: =(W6+X6)-AB6 -> 12900 | Z6: =(W6+X6)/D6 -> 430 | AA6: =W6*45% -> 5805 | AB6: =Q6*Z6 -> 0 | AD6: =(AC6)*Z6 -> 0 | AE6: =T6 -> 0 | AG6: =ROUNDUP(AA6*12%,0) -> 697 | AH6: =ROUNDUP((Y6+X6)*0.75%,0) -> 97 | AI6: =SUM(AB6,AD6:AH6) -> 794 | AJ6: =ROUND(SUM(W6:X6)-AI6,0) -> 12106 | AK6: =ROUNDUP(AA6*13.01%,0) -> 756 | AL6: =ROUNDUP((Y6+X6)*3.25%,0) -> 420 | AN6: 1750059000000281
A7: TOTAL | R7: =SUM(R5:R6) -> 0 | S7: =SUM(S5:S6) -> 0 | T7: =SUM(T5:T6) -> 0 | U7: =SUM(U5:U6) -> 0 | V7: =SUM(V5:V6) -> 22300 | W7: =SUM(W5:W6) -> 22300 | X7: =SUM(X5:X6) -> 0 | Y7: =SUM(Y5:Y6) -> 22300 | ... AM7: =SUM(AM5:AM6) -> 0 | AO7: =SUM(AO5:AO6) -> 0
A8: HR Manager | U8: Finance Manager | AL8: Joint Director - Admin

Sheet Securities
A1: QUEEN MIRA INTERNATIONAL SCHOOL
A2: SECURITIES - SALARY STATEMENT JUNE 2026
A3: S.No | B3: Name | C3: Department | D3: Attendance | R3: Salary Advance / Loan Details | V3: Gross Salary | W3: Payable Gross Salary | X3: Other Allownace | Y3: Salary.Actuals [Gross Salary - Leave Deduction] | Z3: Salary per day [Gross salary / no of days that month] | AA3: Basic [45% of Gross Salary] | AB3: Deductions | AJ3: Net Salary | AK3: QMIS Contribution | AM3: Remarks
D4: Total working days | E4: Lates. Actuals | F4: Lates. Leave [Exceeding lates conversions count] | G4: Final Lates after deducting exceeding Late leaves | H4: Permissions.Actuals | I4: Exceeding Permissions taken for this month | J4: Proper Permissions | K4: Proper Casual Leave already taken for this year till date | L4: Proper Casual Leave taken for this month | M4: Exceeding Casual Leave taken for this month / Memo issued | N4: Absent / Suspension.Actuals | O4: Gardening / Other Leave | P4: Total Leave days.Actuals | Q4: Loss of Pay Days | R4: Total Loan Amount | S4: Amount already paid | T4: Amount to be paid for this month | U4: Remaining Loan Amount | AB4: Leave / Absent / Permission Leave / Late Leave | AC4: Not Punched Days | AD4: Not Punched LOP | AE4: Salary Advance / Loan | AF4: Special Deductions [Telephone Bill + Laptop + Uniform + Trainings etc] | AG4: PF [12% of Basic Salary] | AH4: ESI [0.75% of Salary.Actuals] | AI4: Total | AK4: PF [13.01% of Basic Salary] | AL4: ESI [3.25% of Salary.Actuals]
A5: 1 | B5: VAIRAMANI S/O BOSE | C5: Child Safety Officer | D5: 30 | E5: 0 | F5: =IF((E5/3)>=1,TRUNC(E5/3,0),0) -> 0 | G5: =E5-F5*3 -> 0 | H5: 2 | I5: =IF(H5<2,H5,H5-2) -> 0 | J5: =H5-I5 -> 2 | K5: 0 | L5: 0.5 | M5: 0 | N5: 0 | O5: 0 | P5: =L5+M5+N5+O5 -> 0.5 | Q5: =(F5*0.5)+(I5*0.5)+L5+(N5*2)+M5 -> 0.5 | R5: =150000+200000+50000 -> 400000 | S5: =87000+10000+10000+10000+10000+10000+10000+10000+10000+10000+10000+10000+10000+10000+10000+10000+10000+10000 -> 257000 | T5: 10000 | U5: =R5-(S5+T5) -> 133000 | V5: 25000 | W5: =V5 -> 25000 | X5: 0 | Y5: =W5-AB5 -> 24583.333 | Z5: =W5/D5 -> 833.33333 | AA5: =W5*45% -> 11250 | AB5: =Q5*Z5 -> 416.66667 | AD5: =(AC5)*Z5 -> 0 | AE5: =T5 -> 10000 | AG5: 0 | AH5: 0 | AI5: =SUM(AB5,AD5:AH5) -> 10416.667 | AJ5: =ROUND(SUM(W5:X5)-AI5,0) -> 14583 | AK5: 0 | AL5: 0 | AM5: Salary Adv Note 4 Pg.No: 7. | AN5: 1750059000000196
A6: 2 | B6: MOHAMED ALI JINNA A | C6: Security Officer | D6: 30 | E6: 0 | F6: =IF((E6/3)>=1,TRUNC(E6/3,0),0) -> 0 | G6: =E6-F6*3 -> 0 | H6: 2 | I6: =IF(H6<2,H6,H6-2) -> 0 | J6: =H6-I6 -> 2 | K6: 0 | L6: 0 | M6: 0 | N6: 0 | O6: 0 | P6: =L6+M6+N6+O6 -> 0 | Q6: =(F6*0.5)+(I6*0.5)+L6+(N6*2)+M6 -> 0 | U6: =R6-(S6+T6) -> 0 | V6: 19300 | W6: =V6 -> 19300 | X6: 0 | Y6: =W6-AB6 -> 19300 | Z6: =W6/D6 -> 643.33333 | AA6: =W6*45% -> 8685 | AB6: =Q6*Z6 -> 0 | AD6: =(AC6)*Z6 -> 0 | AE6: =T6 -> 0 | AG6: 0 | AH6: 0 | AI6: =SUM(AB6,AD6:AH6) -> 0 | AJ6: =ROUND(SUM(W6:X6)-AI6,0) -> 19300 | AK6: 0 | AL6: 0 | AN6: 1750060000000380
A7: TOTAL | R7: =SUM(R5:R6) -> 400000 | S7: =SUM(S5:S6) -> 257000 | T7: =SUM(T5:T6) -> 10000 | U7: =SUM(U5:U6) -> 133000 | V7: =SUM(V5:V6) -> 44300 | W7: =SUM(W5:W6) -> 44300 | X7: =SUM(X5:X6) -> 0 | Y7: =SUM(Y5:Y6) -> 43883.333 | ... AM7: =SUM(AM5:AM6) -> 0
A8: HR Manager | U8: Finance Manager | AL8: Joint Director - Admin

Sheet House Keeping
A1: QUEEN MIRA INTERNATIONAL SCHOOL
A2: HOUSE KEEPING - SALARY STATEMENT JUNE 2026
A3: S.No | B3: Name | C3: Department | D3: Attendance | R3: Salary Advance / Loan Details | V3: Gross Salary | W3: Payable Gross Salary | X3: Other Allownace | Y3: Salary.Actuals [Gross Salary - Leave Deduction] | Z3: Salary per day [Gross salary / no of days that month] | AA3: Basic [45% of Gross Salary] | AB3: Deductions | AJ3: Net Salary | AK3: QMIS Contribution | AM3: Remarks
D4: Total working days | E4: Lates. Actuals | F4: Lates. Leave [Exceeding lates conversions count] | G4: Final Lates after deducting exceeding Late leaves | H4: Permissions.Actuals | I4: Exceeding Permissions taken for this month | J4: Proper Permissions | K4: Proper Casual Leave already taken for this year till date | L4: Proper Casual Leave taken for this month | M4: Exceeding Casual Leave taken for this month / Memo issued | N4: Absent / Suspension.Actuals | O4: Gardening / Other Leave | P4: Total Leave days.Actuals | Q4: Loss of Pay Days | R4: Total Loan Amount | S4: Amount already paid | T4: Amount to be paid for this month | U4: Remaining Loan Amount | AB4: Leave / Absent / Permission Leave / Late Leave | AC4: Not Punched Days | AD4: Not Punched LOP | AE4: Salary Advance / Loan | AF4: Special Deductions [Telephone Bill + Laptop + Uniform + Trainings etc] | AG4: PF [12% of Basic Salary] | AH4: ESI [0.75% of Salary.Actuals] | AI4: Total | AK4: PF [13.01% of Basic Salary] | AL4: ESI [3.25% of Salary.Actuals]
A5: 1 | B5: AMARAVALLI W/O RAJANGAM | C5: Janitor | D5: 30 | E5: 0 | F5: =IF((E5/3)>=1,TRUNC(E5/3,0),0) -> 0 | G5: =E5-F5*3 -> 0 | H5: 0 | I5: =IF(H5<1,H5,H5-1) -> 0 | J5: =H5-I5 -> 0 | K5: 0 | L5: 0 | M5: 0 | N5: 0 | O5: 0 | P5: =L5+M5+N5+O5 -> 0 | Q5: =(F5*0.5)+(I5*0.5)+M5+(N5*2) -> 0 | U5: =R5-(S5+T5) -> 0 | V5: 14300 | W5: =V5 -> 14300 | Y5: =(W5+X5)-AB5 -> 14300 | Z5: =W5/D5 -> 476.66667 | AA5: =W5*45% -> 6435 | AB5: =Q5*Z5 -> 0 | AD5: =(AC5)*Z5 -> 0 | AE5: =T5 -> 0 | AG5: =ROUNDUP(AA5*12%,0) -> 773 | AH5: =ROUNDUP((Y5+X5)*0.75%,0) -> 108 | AI5: =SUM(AB5,AD5:AH5) -> 881 | AJ5: =ROUND(SUM(W5:X5)-AI5,0) -> 13419 | AK5: =ROUNDUP(AA5*13.01%,0) -> 838 | AL5: =ROUNDUP((Y5+X5)*3.25%,0) -> 465 | AN5: 1750060000000886
A6: 2 | B6: PARVATHI W/O MUTHAIAH | C6: Janitor | D6: 30 | E6: 0 | F6: =IF((E6/3)>=1,TRUNC(E6/3,0),0) -> 0 | G6: =E6-F6*3 -> 0 | H6: 0 | I6: =IF(H6<2,H6,H6-2) -> 0 | J6: =H6-I6 -> 0 | K6: 0 | L6: 1 | M6: 0 | N6: 0 | O6: 0 | P6: =L6+M6+N6+O6 -> 1 | Q6: =(F6*0.5)+(I6*0.5)+M6+(N6*2) -> 0 | R6: 20000 | S6: =2000+2000+2000+2000+2000+2000+2000 -> 14000 | T6: 2000 | U6: =R6-(S6+T6) -> 4000 | V6: 13500 | W6: =V6 -> 13500 | Y6: =(W6+X6)-AB6 -> 13500 | Z6: =W6/D6 -> 450 | AA6: =W6*45% -> 6075 | AB6: =Q6*Z6 -> 0 | AD6: =(AC6)*Z6 -> 0 | AE6: =T6 -> 2000 | AG6: =ROUNDUP(AA6*12%,0) -> 729 | AH6: =ROUNDUP((Y6+X6)*0.75%,0) -> 102 | AI6: =SUM(AB6,AD6:AH6) -> 2831 | AJ6: =ROUND(SUM(W6:X6)-AI6,0) -> 10669 | AK6: =ROUNDUP(AA6*13.01%,0) -> 791 | AL6: =ROUNDUP((Y6+X6)*3.25%,0) -> 439 | AM6: Salary Adv Note: 4Pg.No: 30 | AN6: 1750059000000231
A7: TOTAL | R7: =SUM(R5:R6) -> 20000 | S7: =SUM(S5:S6) -> 14000 | T7: =SUM(T5:T6) -> 2000 | U7: =SUM(U5:U6) -> 4000 | V7: =SUM(V5:V6) -> 27800 | W7: =SUM(W5:W6) -> 27800 | X7: =SUM(X5:X6) -> 0 | Y7: =SUM(Y5:Y6) -> 27800 | ... AM7: =SUM(AM5:AM6) -> 0
A8: HR Manager | W8: Finance Manager | AL8: Joint Director - Admin

Sheet Kindly Pay Salary Pay
E1: Teaching | J1: Admin | O1: Driver | T1: ECA Regular
T2: S. No | U2: Name | V2: Account Number | W2: Amount
E3: S. No | F3: Name | G3: Account Number | H3: Amount | J3: S. No | K3: Name | L3: Account Number | M3: Amount | O3: S. No | P3: Name | Q3: Account Number | R3: Amount | T3: =#REF! -> #REF! | U3: =#REF! -> #REF! | V3: =#REF! -> #REF! | W3: =#REF! -> #REF!
E4: =Academics!A5 -> 1 | F4: =Academics!B5 -> SUJATHA D/O SUBBURAM | G4: =Academics!AN5 -> 1750155000050628 | H4: =Academics!AJ5 -> 102700 | J4: =Admin!A5 -> 1 | K4: =Admin!B5 -> JOSEPHINE ANNE SHEEBHA ARULDASS | L4: =Admin!AN5 -> 1750062000000072 | M4: =Admin!AJ5 -> 67700 | O4: =Drivers!A5 -> 1 | P4: =Drivers!B5 -> KUMARAVEL MOOKKAIAH | Q4: =Drivers!AN5 -> 1750060000000508 | R4: =Drivers!AJ5 -> 22231 | T4: =#REF! -> #REF! | U4: =#REF! -> #REF! | V4: =#REF! -> #REF! | W4: =#REF! -> #REF!
E5: =Academics!A6 -> 2 | F5: =Academics!B6 -> A JAINCOL FATHIMA | G5: =Academics!AN6 -> 1750061000000064 | H5: =Academics!AJ6 -> 0 | J5: =Admin!A6 -> 2 | K5: =Admin!B6 -> Jeya Dharini Abinath | L5: =Admin!AN6 -> 0 | M5: =Admin!AJ6 -> 24500 | O5: =Drivers!A6 -> 2 | P5: =Drivers!B6 -> DURAIMURUGAN NAGARAJAN | Q5: =Drivers!AN6 -> 1750060000000522 | R5: =Drivers!AJ6 -> 18991 | T5: =#REF! -> #REF! | U5: =#REF! -> #REF! | V5: =#REF! -> #REF! | W5: =#REF! -> #REF!
E6: =Academics!#REF! -> #REF! | F6: =Academics!#REF! -> #REF! | G6: =Academics!#REF! -> #REF! | H6: =Academics!#REF! -> #REF! | J6: =Admin!#REF! -> #REF! | K6: =Admin!#REF! -> #REF! | L6: =Admin!#REF! -> #REF! | M6: =Admin!#REF! -> #REF! | O6: =Drivers!#REF! -> #REF! | P6: =Drivers!#REF! -> #REF! | Q6: =Drivers!#REF! -> #REF! | R6: =Drivers!#REF! -> #REF! | T6: =#REF! -> #REF! | U6: =#REF! -> #REF! | V6: =#REF! -> #REF! | W6: =#REF! -> #REF!
E7: =Academics!#REF! -> #REF! | F7: =Academics!#REF! -> #REF! | G7: =Academics!#REF! -> #REF! | H7: =Academics!#REF! -> #REF! | J7: =Admin!#REF! -> #REF! | K7: =Admin!#REF! -> #REF! | L7: =Admin!#REF! -> #REF! | M7: =Admin!#REF! -> #REF! | O7: =Drivers!#REF! -> #REF! | P7: =Drivers!#REF! -> #REF! | Q7: =Drivers!#REF! -> #REF! | R7: =Drivers!#REF! -> #REF! | T7: =#REF! -> #REF! | U7: =#REF! -> #REF! | V7: =#REF! -> #REF! | W7: =#REF! -> #REF!
E8: =Academics!#REF! -> #REF! | F8: =Academics!#REF! -> #REF! | G8: =Academics!#REF! -> #REF! | H8: =Academics!#REF! -> #REF! | J8: =Admin!#REF! -> #REF! | K8: =Admin!#REF! -> #REF! | L8: =Admin!#REF! -> #REF! | M8: =Admin!#REF! -> #REF! | O8: =Drivers!#REF! -> #REF! | P8: =Drivers!#REF! -> #REF! | Q8: =Drivers!#REF! -> #REF! | R8: =Drivers!#REF! -> #REF! | T8: =#REF! -> #REF! | U8: =#REF! -> #REF! | V8: =#REF! -> #REF! | W8: =#REF! -> #REF!
E9: =Academics!#REF! -> #REF! | F9: =Academics!#REF! -> #REF! | G9: =Academics!#REF! -> #REF! | H9: =Academics!#REF! -> #REF! | J9: =Admin!#REF! -> #REF! | K9: =Admin!#REF! -> #REF! | L9: =Admin!#REF! -> #REF! | M9: =Admin!#REF! -> #REF! | O9: =Drivers!#REF! -> #REF! | P9: =Drivers!#REF! -> #REF! | Q9: =Drivers!#REF! -> #REF! | R9: =Drivers!#REF! -> #REF! | T9: =#REF! -> #REF! | U9: =#REF! -> #REF! | V9: =#REF! -> #REF! | W9: =#REF! -> #REF!
E10: =Academics!#REF! -> #REF! | F10: =Academics!#REF! -> #REF! | G10: =Academics!#REF! -> #REF! | H10: =Academics!#REF! -> #REF! | J10: =Admin!#REF! -> #REF! | K10: =Admin!#REF! -> #REF! | L10: =Admin!#REF! -> #REF! | M10: =Admin!#REF! -> #REF! | O10: =Drivers!#REF! -> #REF! | P10: =Drivers!#REF! -> #REF! | Q10: =Drivers!#REF! -> #REF! | R10: =Drivers!#REF! -> #REF! | T10: =#REF! -> #REF! | U10: =#REF! -> #REF! | V10: =#REF! -> #REF! | W10: =#REF! -> #REF!
E11: =Academics!#REF! -> #REF! | F11: =Academics!#REF! -> #REF! | G11: =Academics!#REF! -> #REF! | H11: =Academics!#REF! -> #REF! | J11: =Admin!#REF! -> #REF! | K11: =Admin!#REF! -> #REF! | L11: =Admin!#REF! -> #REF! | M11: =Admin!#REF! -> #REF! | O11: =Drivers!#REF! -> #REF! | P11: =Drivers!#REF! -> #REF! | Q11: =Drivers!#REF! -> #REF! | R11: =Drivers!#REF! -> #REF! | T11: =#REF! -> #REF! | U11: =#REF! -> #REF! | V11: =#REF! -> #REF! | W11: =#REF! -> #REF!
E12: =Academics!#REF! -> #REF! | F12: =Academics!#REF! -> #REF! | G12: =Academics!#REF! -> #REF! | H12: =Academics!#REF! -> #REF! | J12: ='Relieved Admin'!#REF! -> #REF! | K12: ='Relieved Admin'!#REF! -> #REF! | L12: ='Relieved Admin'!#REF! -> #REF! | M12: ='Relieved Admin'!#REF! -> #REF! | O12: =Drivers!#REF! -> #REF! | P12: =Drivers!#REF! -> #REF! | Q12: =Drivers!#REF! -> #REF! | R12: =Drivers!#REF! -> #REF! | T12: =#REF! -> #REF! | U12: =#REF! -> #REF! | V12: =#REF! -> #REF! | W12: =#REF! -> #REF!
E13: =Academics!#REF! -> #REF! | F13: =Academics!#REF! -> #REF! | G13: =Academics!#REF! -> #REF! | H13: =Academics!#REF! -> #REF! | J13: =Admin!#REF! -> #REF! | K13: =Admin!#REF! -> #REF! | L13: =Admin!#REF! -> #REF! | M13: =Admin!#REF! -> #REF! | O13: =Drivers!#REF! -> #REF! | P13: =Drivers!#REF! -> #REF! | Q13: =Drivers!#REF! -> #REF! | R13: =Drivers!#REF! -> #REF! | T13: =#REF! -> #REF! | U13: =#REF! -> #REF! | V13: =#REF! -> #REF! | W13: =#REF! -> #REF!
E14: =Academics!#REF! -> #REF! | F14: =Academics!#REF! -> #REF! | G14: =Academics!#REF! -> #REF! | H14: =Academics!#REF! -> #REF! | J14: ='Relieved Admin'!A5 -> 1 | K14: ='Relieved Admin'!B5 -> DEEPIKA KANNAN | L14: ='Relieved Admin'!AN5 -> 1750060000000023 | M14: ='Relieved Admin'!AJ5 -> 6667 | O14: =Drivers!#REF! -> #REF! | P14: =Drivers!#REF! -> #REF! | Q14: =Drivers!#REF! -> #REF! | R14: =Drivers!#REF! -> #REF! | T14: =#REF! -> #REF! | U14: =#REF! -> #REF! | V14: =#REF! -> #REF! | W14: =#REF! -> #REF!
E15: =Academics!#REF! -> #REF! | F15: =Academics!#REF! -> #REF! | G15: =Academics!#REF! -> #REF! | H15: =Academics!#REF! -> #REF! | J15: =Admin!#REF! -> #REF! | K15: =Admin!#REF! -> #REF! | L15: =Admin!#REF! -> #REF! | M15: =Admin!#REF! -> #REF! | O15: =Drivers!#REF! -> #REF! | P15: =Drivers!#REF! -> #REF! | Q15: =Drivers!#REF! -> #REF! | R15: =Drivers!#REF! -> #REF!
E16: =Academics!#REF! -> #REF! | F16: =Academics!#REF! -> #REF! | G16: =Academics!#REF! -> #REF! | H16: =Academics!#REF! -> #REF! | J16: =Admin!#REF! -> #REF! | K16: =Admin!#REF! -> #REF! | L16: =Admin!#REF! -> #REF! | M16: =Admin!#REF! -> #REF! | O16: =Drivers!#REF! -> #REF! | P16: =Drivers!#REF! -> #REF! | Q16: =Drivers!#REF! -> #REF! | R16: =Drivers!#REF! -> #REF!
E17: =Academics!#REF! -> #REF! | F17: =Academics!#REF! -> #REF! | G17: =Academics!#REF! -> #REF! | H17: =Academics!#REF! -> #REF! | J17: =Admin!#REF! -> #REF! | K17: =Admin!#REF! -> #REF! | L17: =Admin!#REF! -> #REF! | M17: =Admin!#REF! -> #REF! | O17: ='Relieved Admin'!#REF! -> #REF! | P17: ='Relieved Admin'!#REF! -> #REF! | Q17: ='Relieved Admin'!#REF! -> #REF! | R17: ='Relieved Admin'!#REF! -> #REF!
E18: =Academics!#REF! -> #REF! | F18: =Academics!#REF! -> #REF! | G18: =Academics!#REF! -> #REF! | H18: =Academics!#REF! -> #REF! | J18: =Admin!#REF! -> #REF! | K18: =Admin!#REF! -> #REF! | L18: =Admin!#REF! -> #REF! | M18: =Admin!#REF! -> #REF! | O18: =Drivers!#REF! -> #REF! | P18: =Drivers!#REF! -> #REF! | Q18: =Drivers!#REF! -> #REF! | R18: =Drivers!#REF! -> #REF!
E19: =Academics!#REF! -> #REF! | F19: =Academics!#REF! -> #REF! | G19: =Academics!#REF! -> #REF! | H19: =Academics!#REF! -> #REF! | J19: =Admin!#REF! -> #REF! | K19: =Admin!#REF! -> #REF! | L19: =Admin!#REF! -> #REF! | M19: =Admin!#REF! -> #REF! | O19: ='Relieved Admin'!#REF! -> #REF! | P19: ='Relieved Admin'!#REF! -> #REF! | Q19: ='Relieved Admin'!#REF! -> #REF! | R19: ='Relieved Admin'!#REF! -> #REF!
E20: =Academics!#REF! -> #REF! | F20: =Academics!#REF! -> #REF! | G20: =Academics!#REF! -> #REF! | H20: =Academics!#REF! -> #REF! | J20: =Admin!#REF! -> #REF! | K20: =Admin!#REF! -> #REF! | L20: =Admin!#REF! -> #REF! | M20: =Admin!#REF! -> #REF! | O20: =Drivers!A7 -> TOTAL | R20: =Drivers!AJ7 -> 41222
E21: =Academics!#REF! -> #REF! | F21: =Academics!#REF! -> #REF! | G21: =Academics!#REF! -> #REF! | H21: =Academics!#REF! -> #REF! | J21: =Admin!#REF! -> #REF! | K21: =Admin!#REF! -> #REF! | L21: =Admin!#REF! -> #REF! | M21: =Admin!#REF! -> #REF!
E22: =Academics!#REF! -> #REF! | F22: =Academics!#REF! -> #REF! | G22: =Academics!#REF! -> #REF! | H22: =Academics!#REF! -> #REF! | J22: =Admin!#REF! -> #REF! | K22: =Admin!#REF! -> #REF! | L22: =Admin!#REF! -> #REF! | M22: =Admin!#REF! -> #REF!
E23: =Academics!#REF! -> #REF! | F23: =Academics!#REF! -> #REF! | G23: =Academics!#REF! -> #REF! | H23: =Academics!#REF! -> #REF! | J23: =Admin!#REF! -> #REF! | K23: =Admin!#REF! -> #REF! | L23: =Admin!#REF! -> #REF! | M23: =Admin!#REF! -> #REF!
E24: =Academics!#REF! -> #REF! | F24: =Academics!#REF! -> #REF! | G24: =Academics!#REF! -> #REF! | H24: =Academics!#REF! -> #REF! | J24: =Admin!#REF! -> #REF! | K24: =Admin!#REF! -> #REF! | L24: =Admin!#REF! -> #REF! | M24: =Admin!#REF! -> #REF!
E25: =Academics!#REF! -> #REF! | F25: =Academics!#REF! -> #REF! | G25: =Academics!#REF! -> #REF! | H25: =Academics!#REF! -> #REF! | J25: =Admin!#REF! -> #REF! | K25: =Admin!#REF! -> #REF! | L25: =Admin!#REF! -> #REF! | M25: =Admin!#REF! -> #REF!
E26: =Academics!#REF! -> #REF! | F26: =Academics!#REF! -> #REF! | G26: =Academics!#REF! -> #REF! | H26: =Academics!#REF! -> #REF! | J26: =Admin!#REF! -> #REF! | K26: =Admin!#REF! -> #REF! | L26: =Admin!#REF! -> #REF! | M26: =Admin!#REF! -> #REF! | O26: Conductors
E27: =Academics!#REF! -> #REF! | F27: =Academics!#REF! -> #REF! | G27: =Academics!#REF! -> #REF! | H27: =Academics!#REF! -> #REF! | J27: =Admin!#REF! -> #REF! | K27: =Admin!#REF! -> #REF! | L27: =Admin!#REF! -> #REF! | M27: =Admin!#REF! -> #REF! | O27: =Conductors!A5 -> 1 | P27: =Conductors!B5 -> SUNDARI JEYARAM | Q27: =Conductors!AN5 -> 1750059000000054 | R27: =Conductors!AJ5 -> 9400
E28: =Academics!#REF! -> #REF! | F28: =Academics!#REF! -> #REF! | G28: =Academics!#REF! -> #REF! | H28: =Academics!#REF! -> #REF! | J28: =Admin!#REF! -> #REF! | K28: =Admin!#REF! -> #REF! | L28: =Admin!#REF! -> #REF! | M28: =Admin!#REF! -> #REF! | O28: =Conductors!A6 -> 2 | P28: =Conductors!B6 -> S CHITRA | Q28: =Conductors!AN6 -> 1750059000000281 | R28: =Conductors!AJ6 -> 12106
E29: ='Relieved Academics'!#REF! -> #REF! | F29: ='Relieved Academics'!#REF! -> #REF! | G29: ='Relieved Academics'!#REF! -> #REF! | H29: ='Relieved Academics'!#REF! -> #REF! | J29: =Admin!#REF! -> #REF! | K29: =Admin!#REF! -> #REF! | L29: =Admin!#REF! -> #REF! | M29: =Admin!#REF! -> #REF! | O29: =Conductors!#REF! -> #REF! | P29: =Conductors!#REF! -> #REF! | Q29: =Conductors!#REF! -> #REF! | R29: =Conductors!#REF! -> #REF!
E30: =Academics!#REF! -> #REF! | F30: =Academics!#REF! -> #REF! | G30: =Academics!#REF! -> #REF! | H30: =Academics!#REF! -> #REF! | J30: =Admin!#REF! -> #REF! | K30: =Admin!#REF! -> #REF! | L30: =Admin!#REF! -> #REF! | M30: =Admin!#REF! -> #REF! | O30: =Conductors!#REF! -> #REF! | P30: =Conductors!#REF! -> #REF! | Q30: =Conductors!#REF! -> #REF! | R30: =Conductors!#REF! -> #REF!
E31: =Academics!#REF! -> #REF! | F31: =Academics!#REF! -> #REF! | G31: =Academics!#REF! -> #REF! | H31: =Academics!#REF! -> #REF! | J31: =Admin!#REF! -> #REF! | K31: =Admin!#REF! -> #REF! | L31: =Admin!#REF! -> #REF! | M31: =Admin!#REF! -> #REF! | O31: =Conductors!#REF! -> #REF! | P31: =Conductors!#REF! -> #REF! | Q31: =Conductors!#REF! -> #REF! | R31: =Conductors!#REF! -> #REF!
E32: =Academics!#REF! -> #REF! | F32: =Academics!#REF! -> #REF! | G32: =Academics!#REF! -> #REF! | H32: =Academics!#REF! -> #REF! | J32: =Admin!#REF! -> #REF! | K32: =Admin!#REF! -> #REF! | L32: =Admin!#REF! -> #REF! | M32: =Admin!#REF! -> #REF! | O32: =Conductors!#REF! -> #REF! | P32: =Conductors!#REF! -> #REF! | Q32: =Conductors!#REF! -> #REF! | R32: =Conductors!#REF! -> #REF!
E33: =Academics!#REF! -> #REF! | F33: =Academics!#REF! -> #REF! | G33: =Academics!#REF! -> #REF! | H33: =Academics!#REF! -> #REF! | J33: =Admin!#REF! -> #REF! | K33: =Admin!#REF! -> #REF! | L33: =Admin!#REF! -> #REF! | M33: =Admin!#REF! -> #REF! | O33: =Conductors!#REF! -> #REF! | P33: =Conductors!#REF! -> #REF! | Q33: =Conductors!#REF! -> #REF! | R33: =Conductors!#REF! -> #REF!
E34: =Academics!#REF! -> #REF! | F34: =Academics!#REF! -> #REF! | G34: =Academics!#REF! -> #REF! | H34: =Academics!#REF! -> #REF! | J34: =Admin!#REF! -> #REF! | K34: =Admin!#REF! -> #REF! | L34: =Admin!#REF! -> #REF! | M34: =Admin!#REF! -> #REF! | O34: =Conductors!#REF! -> #REF! | P34: =Conductors!#REF! -> #REF! | Q34: =Conductors!#REF! -> #REF! | R34: =Conductors!#REF! -> #REF!
E35: ='Relieved Academics'!#REF! -> #REF! | F35: ='Relieved Academics'!#REF! -> #REF! | G35: ='Relieved Academics'!#REF! -> #REF! | H35: ='Relieved Academics'!#REF! -> #REF! | J35: =Admin!#REF! -> #REF! | K35: =Admin!#REF! -> #REF! | L35: =Admin!#REF! -> #REF! | M35: =Admin!#REF! -> #REF! | O35: =Conductors!#REF! -> #REF! | P35: =Conductors!#REF! -> #REF! | Q35: =Conductors!#REF! -> #REF! | R35: =Conductors!#REF! -> #REF!
E36: =Academics!#REF! -> #REF! | F36: =Academics!#REF! -> #REF! | G36: =Academics!#REF! -> #REF! | H36: =Academics!#REF! -> #REF! | J36: =Admin!#REF! -> #REF! | K36: =Admin!#REF! -> #REF! | L36: =Admin!#REF! -> #REF! | M36: =Admin!#REF! -> #REF! | O36: =Conductors!#REF! -> #REF! | P36: =Conductors!#REF! -> #REF! | Q36: =Conductors!#REF! -> #REF! | R36: =Conductors!#REF! -> #REF!
E37: =Academics!#REF! -> #REF! | F37: =Academics!#REF! -> #REF! | G37: =Academics!#REF! -> #REF! | H37: =Academics!#REF! -> #REF! | J37: =Admin!#REF! -> #REF! | K37: =Admin!#REF! -> #REF! | L37: =Admin!#REF! -> #REF! | M37: =Admin!#REF! -> #REF! | O37: =Conductors!#REF! -> #REF! | P37: =Conductors!#REF! -> #REF! | Q37: =Conductors!#REF! -> #REF! | R37: =Conductors!#REF! -> #REF!
E38: =Academics!#REF! -> #REF! | F38: =Academics!#REF! -> #REF! | G38: =Academics!#REF! -> #REF! | H38: =Academics!#REF! -> #REF! | J38: =Admin!#REF! -> #REF! | K38: =Admin!#REF! -> #REF! | L38: =Admin!#REF! -> #REF! | M38: =Admin!#REF! -> #REF! | O38: =Conductors!A7 -> TOTAL | R38: =Conductors!AJ7 -> 21506
E39: =Academics!#REF! -> #REF! | F39: =Academics!#REF! -> #REF! | G39: =Academics!#REF! -> #REF! | H39: =Academics!#REF! -> #REF! | J39: ='Relieved Admin'!#REF! -> #REF! | K39: ='Relieved Admin'!#REF! -> #REF! | L39: ='Relieved Admin'!#REF! -> #REF! | M39: ='Relieved Admin'!#REF! -> #REF!
E40: =Academics!#REF! -> #REF! | F40: =Academics!#REF! -> #REF! | G40: =Academics!#REF! -> #REF! | H40: =Academics!#REF! -> #REF! | J40: =Admin!#REF! -> #REF! | K40: =Admin!#REF! -> #REF! | L40: =Admin!#REF! -> #REF! | M40: =Admin!#REF! -> #REF!
E41: =Academics!#REF! -> #REF! | F41: =Academics!#REF! -> #REF! | G41: =Academics!#REF! -> #REF! | H41: =Academics!#REF! -> #REF! | J41: =Admin!#REF! -> #REF! | K41: =Admin!#REF! -> #REF! | L41: =Admin!#REF! -> #REF! | M41: =Admin!#REF! -> #REF!
E42: =Academics!#REF! -> #REF! | F42: =Academics!#REF! -> #REF! | G42: =Academics!#REF! -> #REF! | H42: =Academics!#REF! -> #REF! | J42: =Admin!#REF! -> #REF! | K42: =Admin!#REF! -> #REF! | L42: =Admin!#REF! -> #REF! | M42: =Admin!#REF! -> #REF!
E43: =Academics!#REF! -> #REF! | F43: =Academics!#REF! -> #REF! | G43: =Academics!#REF! -> #REF! | H43: =Academics!#REF! -> #REF! | J43: =Admin!#REF! -> #REF! | K43: =Admin!#REF! -> #REF! | L43: =Admin!#REF! -> #REF! | M43: =Admin!#REF! -> #REF! | O43: Security
E44: =Academics!#REF! -> #REF! | F44: =Academics!#REF! -> #REF! | G44: =Academics!#REF! -> #REF! | H44: =Academics!#REF! -> #REF! | J44: =Admin!#REF! -> #REF! | K44: =Admin!#REF! -> #REF! | L44: =Admin!#REF! -> #REF! | M44: =Admin!#REF! -> #REF! | O44: =Securities!A5 -> 1 | P44: =Securities!B5 -> VAIRAMANI S/O BOSE | Q44: =Securities!AN5 -> 1750059000000196 | R44: =Securities!AJ5 -> 14583
E45: =Academics!#REF! -> #REF! | F45: =Academics!#REF! -> #REF! | G45: =Academics!#REF! -> #REF! | H45: =Academics!#REF! -> #REF! | J45: ='Relieved Admin'!A6 -> 2 | K45: ='Relieved Admin'!B6 -> G B Hemavathy | L45: ='Relieved Admin'!AN6 -> 1750061000000572 | M45: ='Relieved Admin'!AJ6 -> 2800 | O45: =Securities!A6 -> 2 | P45: =Securities!B6 -> MOHAMED ALI JINNA A | Q45: =Securities!AN6 -> 1750060000000380 | R45: =Securities!AJ6 -> 19300
E46: =Academics!#REF! -> #REF! | F46: =Academics!#REF! -> #REF! | G46: =Academics!#REF! -> #REF! | H46: =Academics!#REF! -> #REF! | J46: =Admin!#REF! -> #REF! | K46: =Admin!#REF! -> #REF! | L46: =Admin!#REF! -> #REF! | M46: =Admin!#REF! -> #REF! | O46: =Securities!#REF! -> #REF! | P46: =Securities!#REF! -> #REF! | Q46: =Securities!#REF! -> #REF! | R46: =Securities!#REF! -> #REF!
E47: =Academics!#REF! -> #REF! | F47: =Academics!#REF! -> #REF! | G47: =Academics!#REF! -> #REF! | H47: =Academics!#REF! -> #REF! | J47: =Admin!#REF! -> #REF! | K47: =Admin!#REF! -> #REF! | L47: =Admin!#REF! -> #REF! | M47: =Admin!#REF! -> #REF! | O47: =Securities!#REF! -> #REF! | P47: =Securities!#REF! -> #REF! | Q47: =Securities!#REF! -> #REF! | R47: =Securities!#REF! -> #REF!
E48: =Academics!#REF! -> #REF! | F48: =Academics!#REF! -> #REF! | G48: =Academics!#REF! -> #REF! | H48: =Academics!#REF! -> #REF! | J48: =Admin!#REF! -> #REF! | K48: =Admin!#REF! -> #REF! | L48: =Admin!#REF! -> #REF! | M48: =Admin!#REF! -> #REF! | O48: =Securities!#REF! -> #REF! | P48: =Securities!#REF! -> #REF! | Q48: =Securities!#REF! -> #REF! | R48: =Securities!#REF! -> #REF!
E49: =Academics!#REF! -> #REF! | F49: =Academics!#REF! -> #REF! | G49: =Academics!#REF! -> #REF! | H49: =Academics!#REF! -> #REF! | J49: TOTAL | M49: =Admin!AJ7 -> 92200 | O49: =Securities!#REF! -> #REF! | P49: =Securities!#REF! -> #REF! | Q49: =Securities!#REF! -> #REF! | R49: =Securities!#REF! -> #REF!
E50: =Academics!#REF! -> #REF! | F50: =Academics!#REF! -> #REF! | G50: =Academics!#REF! -> #REF! | H50: =Academics!#REF! -> #REF! | O50: =Securities!A7 -> TOTAL | R50: =Securities!AJ7 -> 33883
E51: ='Relieved Academics'!#REF! -> #REF! | F51: ='Relieved Academics'!#REF! -> #REF! | G51: ='Relieved Academics'!#REF! -> #REF! | H51: ='Relieved Academics'!#REF! -> #REF!
E52: =Academics!#REF! -> #REF! | F52: =Academics!#REF! -> #REF! | G52: =Academics!#REF! -> #REF! | H52: =Academics!#REF! -> #REF!
E53: =Academics!#REF! -> #REF! | F53: =Academics!#REF! -> #REF! | G53: =Academics!#REF! -> #REF! | H53: =Academics!#REF! -> #REF! | J53: THENI
E54: =Academics!#REF! -> #REF! | F54: =Academics!#REF! -> #REF! | G54: =Academics!#REF! -> #REF! | H54: =Academics!#REF! -> #REF!
E55: =Academics!#REF! -> #REF! | F55: =Academics!#REF! -> #REF! | G55: =Academics!#REF! -> #REF! | H55: =Academics!#REF! -> #REF! | J55: ='Theni - Upparpatti'!A5 -> 1 | K55: ='Theni - Upparpatti'!B5 -> SUJATHA D/O SUBBURAM | L55: ='Theni - Upparpatti'!AN5 -> 1750063000000016 | M55: ='Theni - Upparpatti'!AJ5 -> 10000
E56: ='Relieved Academics'!#REF! -> #REF! | F56: ='Relieved Academics'!#REF! -> #REF! | G56: ='Relieved Academics'!#REF! -> #REF! | H56: ='Relieved Academics'!#REF! -> #REF! | J56: ='Theni - Upparpatti'!A6 -> 2 | K56: ='Theni - Upparpatti'!B6 -> JOSEPHINE ANNE SHEEBHA ARULDASS | L56: ='Theni - Upparpatti'!AN6 -> 1750060000002726 | M56: ='Theni - Upparpatti'!AJ6 -> 10000
E57: =Academics!#REF! -> #REF! | F57: =Academics!#REF! -> #REF! | G57: =Academics!#REF! -> #REF! | H57: =Academics!#REF! -> #REF! | J57: ='Theni - Upparpatti'!#REF! -> #REF! | K57: ='Theni - Upparpatti'!#REF! -> #REF! | L57: ='Theni - Upparpatti'!#REF! -> #REF! | M57: ='Theni - Upparpatti'!#REF! -> #REF!
E58: =Academics!#REF! -> #REF! | F58: =Academics!#REF! -> #REF! | G58: =Academics!#REF! -> #REF! | H58: =Academics!#REF! -> #REF! | J58: ='Theni - Upparpatti'!#REF! -> #REF! | K58: ='Theni - Upparpatti'!#REF! -> #REF! | L58: ='Theni - Upparpatti'!#REF! -> #REF! | M58: ='Theni - Upparpatti'!#REF! -> #REF!
E59: =Academics!#REF! -> #REF! | F59: =Academics!#REF! -> #REF! | G59: =Academics!#REF! -> #REF! | H59: =Academics!#REF! -> #REF! | J59: ='Theni - Upparpatti'!A7 -> TOTAL | M59: ='Theni - Upparpatti'!AJ7 -> 20000 | O59: House Keeping
E60: =Academics!#REF! -> #REF! | F60: =Academics!#REF! -> #REF! | G60: =Academics!#REF! -> #REF! | H60: =Academics!#REF! -> #REF! | O60: ='House Keeping'!A5 -> 1 | P60: ='House Keeping'!B5 -> AMARAVALLI W/O RAJANGAM | Q60: ='House Keeping'!AN5 -> 1750060000000886 | R60: ='House Keeping'!AJ5 -> 13419
E61: =Academics!#REF! -> #REF! | F61: =Academics!#REF! -> #REF! | G61: =Academics!#REF! -> #REF! | H61: =Academics!#REF! -> #REF! | O61: ='House Keeping'!A6 -> 2 | P61: ='House Keeping'!B6 -> PARVATHI W/O MUTHAIAH | Q61: ='House Keeping'!AN6 -> 1750059000000231 | R61: ='House Keeping'!AJ6 -> 10669
E62: =Academics!#REF! -> #REF! | F62: =Academics!#REF! -> #REF! | G62: =Academics!#REF! -> #REF! | H62: =Academics!#REF! -> #REF! | J62: ECA | O62: ='House Keeping'!#REF! -> #REF! | P62: ='House Keeping'!#REF! -> #REF! | Q62: ='House Keeping'!#REF! -> #REF! | R62: ='House Keeping'!#REF! -> #REF!
E63: =Academics!#REF! -> #REF! | F63: =Academics!#REF! -> #REF! | G63: =Academics!#REF! -> #REF! | H63: =Academics!#REF! -> #REF! | O63: ='House Keeping'!#REF! -> #REF! | P63: ='House Keeping'!#REF! -> #REF! | Q63: ='House Keeping'!#REF! -> #REF! | R63: ='House Keeping'!#REF! -> #REF!
E64: =Academics!#REF! -> #REF! | F64: =Academics!#REF! -> #REF! | G64: =Academics!#REF! -> #REF! | H64: =Academics!#REF! -> #REF! | J64: ='ECA '!A5 -> 1 | K64: ='ECA '!B5 -> R BALACHANDER | L64: ='ECA '!O5 -> 1750060000000106 | M64: ='ECA '!M5 -> 17500 | O64: ='House Keeping'!#REF! -> #REF! | P64: ='House Keeping'!#REF! -> #REF! | Q64: ='House Keeping'!#REF! -> #REF! | R64: ='House Keeping'!#REF! -> #REF!
E65: =Academics!#REF! -> #REF! | F65: =Academics!#REF! -> #REF! | G65: =Academics!#REF! -> #REF! | H65: =Academics!#REF! -> #REF! | J65: ='ECA '!A6 -> 2 | K65: ='ECA '!B6 -> ARAVINDHU PASHWAN VELAYUTHAM | L65: ='ECA '!O6 -> 1750061000000241 | M65: ='ECA '!M6 -> 10938 | O65: ='House Keeping'!#REF! -> #REF! | P65: ='House Keeping'!#REF! -> #REF! | Q65: ='House Keeping'!#REF! -> #REF! | R65: ='House Keeping'!#REF! -> #REF!
E66: =Academics!#REF! -> #REF! | F66: =Academics!#REF! -> #REF! | G66: =Academics!#REF! -> #REF! | H66: =Academics!#REF! -> #REF! | J66: ='ECA '!A7 -> 3 | K66: ='ECA '!B7 -> J RAJA / Chandra | L66: ='ECA '!O7 -> 1750060000001298 | M66: ='ECA '!M7 -> 13000 | O66: ='House Keeping'!#REF! -> #REF! | P66: ='House Keeping'!#REF! -> #REF! | Q66: ='House Keeping'!#REF! -> #REF! | R66: ='House Keeping'!#REF! -> #REF!
E67: ='Relieved Academics'!A5 -> 1 | F67: ='Relieved Academics'!B5 -> Rajasekar | G67: ='Relieved Academics'!AN5 -> 1750060000003764 | H67: ='Relieved Academics'!AJ5 -> 21000 | J67: ='ECA '!A8 -> 4 | K67: ='ECA '!B8 -> J RAJA / Amutheswaran | L67: ='ECA '!O8 -> 1750060000001298 | M67: ='ECA '!M8 -> 12000 | O67: ='House Keeping'!#REF! -> #REF! | P67: ='House Keeping'!#REF! -> #REF! | Q67: ='House Keeping'!#REF! -> #REF! | R67: ='House Keeping'!#REF! -> #REF!
E68: ='Relieved Academics'!A6 -> 2 | F68: ='Relieved Academics'!B6 -> R Veerachinna Krishnan | G68: ='Relieved Academics'!AN6 -> 1750060000003788 | H68: ='Relieved Academics'!AJ6 -> 25828 | J68: ='ECA '!A9 -> 5 | K68: ='ECA '!B9 -> PRAKASHKUMAR BALAJI | L68: ='ECA '!O9 -> 1750061000000135 | M68: ='ECA '!M9 -> 13000 | O68: ='House Keeping'!#REF! -> #REF! | P68: ='House Keeping'!#REF! -> #REF! | Q68: ='House Keeping'!#REF! -> #REF! | R68: ='House Keeping'!#REF! -> #REF!
E69: =Academics!#REF! -> #REF! | F69: =Academics!#REF! -> #REF! | G69: =Academics!#REF! -> #REF! | H69: =Academics!#REF! -> #REF! | J69: ='ECA '!A10 -> 6 | K69: ='ECA '!B10 -> PRAKASHKUMAR BALAJI | L69: ='ECA '!O10 -> 1750061000000135 | M69: ='ECA '!M10 -> 11000 | O69: ='House Keeping'!#REF! -> #REF! | P69: ='House Keeping'!#REF! -> #REF! | Q69: ='House Keeping'!#REF! -> #REF! | R69: ='House Keeping'!#REF! -> #REF!
E70: =Academics!#REF! -> #REF! | F70: =Academics!#REF! -> #REF! | G70: =Academics!#REF! -> #REF! | H70: =Academics!#REF! -> #REF! | J70: ='ECA '!A11 -> 7 | K70: ='ECA '!B11 -> PRABAKARAN PANDI | L70: ='ECA '!O11 -> 1750060000000132 | M70: ='ECA '!M11 -> 14000 | O70: ='Relieved Admin'!#REF! -> #REF! | P70: ='Relieved Admin'!#REF! -> #REF! | Q70: ='Relieved Admin'!#REF! -> #REF! | R70: ='Relieved Admin'!#REF! -> #REF!
E71: =Academics!#REF! -> #REF! | F71: =Academics!#REF! -> #REF! | G71: =Academics!#REF! -> #REF! | H71: =Academics!#REF! -> #REF! | J71: ='ECA '!A12 -> 8 | K71: ='ECA '!B12 -> HARIPRASATH JAYAKUMAR | L71: ='ECA '!O12 -> 1750061000000265 | M71: ='ECA '!M12 -> 12000 | O71: ='House Keeping'!#REF! -> #REF! | P71: ='House Keeping'!#REF! -> #REF! | Q71: ='House Keeping'!#REF! -> #REF! | R71: ='House Keeping'!#REF! -> #REF!
E72: =Academics!#REF! -> #REF! | F72: =Academics!#REF! -> #REF! | G72: =Academics!#REF! -> #REF! | H72: =Academics!#REF! -> #REF! | J72: ='ECA '!A13 -> 9 | K72: ='ECA '!B13 -> RAJA CHINNASAMI | L72: ='ECA '!O13 -> 1750061000000232 | M72: ='ECA '!M13 -> 17000 | O72: ='House Keeping'!#REF! -> #REF! | P72: ='House Keeping'!#REF! -> #REF! | Q72: ='House Keeping'!#REF! -> #REF! | R72: ='House Keeping'!#REF! -> #REF!
E73: =Academics!#REF! -> #REF! | F73: =Academics!#REF! -> #REF! | G73: =Academics!#REF! -> #REF! | H73: =Academics!#REF! -> #REF! | J73: ='ECA '!A14 -> 10 | K73: ='ECA '!B14 -> JEYA SHREE R | L73: ='ECA '!O14 -> 1750060000000850 | M73: ='ECA '!M14 -> 20500 | O73: ='Relieved Admin'!#REF! -> #REF! | P73: ='Relieved Admin'!#REF! -> #REF! | Q73: ='Relieved Admin'!#REF! -> #REF! | R73: ='Relieved Admin'!#REF! -> #REF!
E74: =Academics!#REF! -> #REF! | F74: =Academics!#REF! -> #REF! | G74: =Academics!#REF! -> #REF! | H74: =Academics!#REF! -> #REF! | J74: ='ECA '!A15 -> 11 | K74: ='ECA '!B15 -> SUBAHARI | L74: ='ECA '!O15 -> 1750061000000253 | M74: ='ECA '!M15 -> 18000 | O74: ='House Keeping'!#REF! -> #REF! | P74: ='House Keeping'!#REF! -> #REF! | Q74: ='House Keeping'!#REF! -> #REF! | R74: ='House Keeping'!#REF! -> #REF!
E75: =Academics!#REF! -> #REF! | F75: =Academics!#REF! -> #REF! | G75: =Academics!#REF! -> #REF! | H75: =Academics!#REF! -> #REF! | J75: ='ECA '!A16 -> 12 | K75: ='ECA '!B16 -> DANIEL MERWIN SELVARAJ | L75: ='ECA '!O16 -> 1750061000000289 | M75: ='ECA '!M16 -> 26000 | O75: ='House Keeping'!#REF! -> #REF! | P75: ='House Keeping'!#REF! -> #REF! | Q75: ='House Keeping'!#REF! -> #REF! | R75: ='House Keeping'!#REF! -> #REF!
E76: =Academics!#REF! -> #REF! | F76: =Academics!#REF! -> #REF! | G76: =Academics!#REF! -> #REF! | H76: =Academics!#REF! -> #REF! | J76: ='ECA '!A17 -> 13 | K76: ='ECA '!B17 -> K KEERTHIGA | L76: ='ECA '!O17 -> '1750060000001300 | M76: ='ECA '!M17 -> 11613 | O76: ='House Keeping'!A7 -> TOTAL | R76: ='House Keeping'!AJ7 -> 24088
E77: TOTAL | H77: =Academics!AJ7 -> 102700 | J77: ='ECA '!A18 -> 14 | K77: ='ECA '!B18 -> ARUNKANTH MURUGAN | L77: ='ECA '!O18 -> 1750061000000348 | M77: ='ECA '!M18 -> 20000
J78: ='ECA '!A19 -> Total | M78: ='ECA '!M19 -> 216551
J86: Hostel | O86: ACA+ECA
J87: =Hostel!A5 -> 1 | K87: =Hostel!B5 -> Pangajam | L87: =Hostel!AN5 -> 1750060000001345 | M87: =Hostel!AJ5 -> 26000 | O87: =AEP!A3 -> S.No | P87: =AEP!B3 -> Name | Q87: =AEP!K3 -> 0 | R87: =AEP!I3 -> Net Salary
J88: =Hostel!A6 -> 2 | K88: =Hostel!B6 -> Meena | L88: =Hostel!AN6 -> 1750060000002123 | M88: =Hostel!AJ6 -> 7000 | O88: =AEP!A4 -> 1 | P88: =AEP!B4 -> Sudha | Q88: =AEP!K4 -> 1750061000000383 | R88: =AEP!I4 -> 0
J89: =Hostel!A7 -> 3 | K89: =Hostel!B7 -> AARTHY SELVAM | L89: =Hostel!AN7 -> 1750060000001274 | M89: =Hostel!AJ7 -> 7500 | O89: =AEP!A5 -> 2 | P89: =AEP!B5 -> Thiribuvan | Q89: =AEP!K5 -> 1750061000000419 | R89: =AEP!I5 -> 0
J90: =Hostel!A8 -> TOTAL | M90: =Hostel!AJ8 -> 40500 | O90: =AEP!#REF! -> #REF! | P90: =AEP!#REF! -> #REF! | Q90: =AEP!#REF! -> #REF! | R90: =AEP!#REF! -> #REF!
O91: =AEP!#REF! -> #REF! | P91: =AEP!#REF! -> #REF! | Q91: =AEP!#REF! -> #REF! | R91: =AEP!#REF! -> #REF!
J92: Academic Part time | O92: =AEP!#REF! -> #REF! | P92: =AEP!#REF! -> #REF! | Q92: =AEP!#REF! -> #REF! | R92: =AEP!#REF! -> #REF!
J93: ='Part time academic'!A4 -> 1 | K93: ='Part time academic'!B4 -> Chandrashekaran | L93: ='Part time academic'!L4 -> Cash | M93: ='Part time academic'!J4 -> 57600 | O93: =AEP!#REF! -> #REF! | P93: =AEP!#REF! -> #REF! | Q93: =AEP!#REF! -> #REF! | R93: =AEP!#REF! -> #REF!
J94: ='Part time academic'!#REF! -> #REF! | K94: ='Part time academic'!#REF! -> #REF! | L94: ='Part time academic'!#REF! -> #REF! | M94: ='Part time academic'!#REF! -> #REF! | O94: =AEP!A6 -> Total | R94: =AEP!I6 -> 0
J95: ='Part time academic'!A5 -> 3 | K95: ='Part time academic'!B5 -> Thirubuvan | L95: ='Part time academic'!L5 -> 1750061000000419 | M95: ='Part time academic'!J5 -> 44592
J96: ='Part time academic'!A6 -> 4 | K96: ='Part time academic'!B6 -> Naveen Kumar | L96: ='Part time academic'!L6 -> 1750060000001215 | M96: ='Part time academic'!J6 -> 19333
J97: ='Part time academic'!A7 -> 5 | K97: ='Part time academic'!B7 -> KALPANA KARTHIK S | L97: ='Part time academic'!L7 -> 1750062000000034 | M97: ='Part time academic'!J7 -> 36000
J98: ='Part time academic'!#REF! -> #REF! | K98: ='Part time academic'!#REF! -> #REF! | L98: ='Part time academic'!#REF! -> #REF! | M98: ='Part time academic'!#REF! -> #REF!
J99: ='Part time academic'!A8 -> 6 | K99: ='Part time academic'!B8 -> MATCHIPIRAI MALIKA KATHEROLI | L99: ='Part time academic'!L8 -> 1750061000000312 | M99: ='Part time academic'!J8 -> 44000
J100: ='Part time academic'!A9 -> 7 | K100: ='Part time academic'!B9 -> I PRADEEP CHRISTOPHER | L100: ='Part time academic'!L9 -> 1750061000000362 | M100: ='Part time academic'!J9 -> 29000
J101: ='Part time academic'!A10 -> 8 | K101: ='Part time academic'!B10 -> DHARANI W/O SRINIVAS | L101: ='Part time academic'!L10 -> 1750061000000220 | M101: ='Part time academic'!J10 -> 46000
J102: ='Part time academic'!#REF! -> #REF! | K102: ='Part time academic'!#REF! -> #REF! | L102: ='Part time academic'!#REF! -> #REF! | M102: ='Part time academic'!#REF! -> #REF!
J103: ='Part time academic'!A11 -> 9 | K103: ='Part time academic'!B11 -> Jeyabal J | L103: ='Part time academic'!L11 -> 1105155000093166 | M103: ='Part time academic'!J11 -> 2700
J104: ='Part time academic'!A12 -> 11 | K104: ='Part time academic'!B12 -> Niveth Oliviya | L104: ='Part time academic'!L12 -> 1750060000001203 | M104: ='Part time academic'!J12 -> 0
J105: ='Part time academic'!A14 -> Total | M105: ='Part time academic'!J14 -> 279225
J108: Academic Part time
J109: =AEP!A4 -> 1 | K109: =AEP!B4 -> Sudha | L109: =AEP!K4 -> 1750061000000383 | M109: =AEP!I4 -> 0
...

Sheet Hostel
A1: QUEEN MIRA INTERNATIONAL SCHOOL
A2: HOSTEL - SALARY STATEMENT JUNE 2026
A3: S.No | B3: Name | C3: Department | D3: Attendance | R3: Salary Advance / Loan Details | V3: Gross Salary | W3: Payable Gross Salary | X3: Other Allownace | Y3: Salary.Actuals [Gross Salary - Leave Deduction] | Z3: Salary per day [Gross salary / no of days that month] | AA3: Basic [45% of Gross Salary] | AB3: Deductions | AJ3: Net Salary | AK3: QMIS Contribution | AM3: Remarks
D4: Total working days | E4: Lates. Actuals | F4: Lates. Leave [Exceeding lates conversions count] | G4: Final Lates after deducting exceeding Late leaves | H4: Permissions.Actuals | I4: Exceeding Permissions taken for this month | J4: Proper Permissions | K4: Proper Casual Leave already taken for this year till date | L4: Proper Casual Leave taken for this month | M4: Exceeding Casual Leave taken for this month / Memo issued | N4: Absent / Suspension.Actuals | O4: Gardening / Other Leave | P4: Total Leave days.Actuals | Q4: Loss of Pay Days | R4: Total Loan Amount | S4: Amount already paid | T4: Amount to be paid for this month | U4: Remaining Loan Amount | AB4: Leave / Absent / Permission Leave / Late Leave | AC4: Not Punched Days | AD4: Not Punched LOP | AE4: Salary Advance / Loan | AF4: Special Deductions [Telephone Bill + Laptop + Uniform + Trainings etc] | AG4: PF [12% of Basic Salary] | AH4: ESI [0.75% of Salary.Actuals] | AI4: Total | AK4: PF [13.01% of Basic Salary] | AL4: ESI [3.25% of Salary.Actuals]
A5: 1 | B5: Pangajam | C5: Chef | D5: 30 | E5: 0 | F5: =IF((E5/3)>=1,TRUNC(E5/3,0),0) -> 0 | G5: =E5-F5*3 -> 0 | H5: 0 | I5: =IF(H5<2,H5,H5-2) -> 0 | J5: =H5-I5 -> 0 | K5: 0 | L5: 0 | M5: 0 | N5: 0 | O5: 0 | P5: =L5+M5+N5+O5 -> 0 | Q5: =(F5*0.5)+(I5*0.5)+L5+(N5*2)+M5 -> 0 | T5: 0 | U5: =R5-(S5+T5) -> 0 | V5: 26000 | W5: =V5 -> 26000 | X5: 0 | Y5: =V5-AB5 -> 26000 | Z5: =(V5+X5)/31 -> 838.70968 | AA5: =V5*45% -> 11700 | AB5: =Q5*Z5 -> 0 | AD5: =(AC5)*Z5 -> 0 | AE5: =T5 -> 0 | AG5: 0 | AH5: 0 | AI5: =SUM(AB5,AD5:AH5) -> 0 | AJ5: =ROUND(SUM(W5:X5)-AI5,0) -> 26000 | AK5: 0 | AL5: 0 | AN5: 1750060000001345
A6: 2 | B6: Meena | C6: Chef | D6: 30 | E6: 0 | F6: =IF((E6/3)>=1,TRUNC(E6/3,0),0) -> 0 | G6: =E6-F6*3 -> 0 | H6: 0 | I6: =IF(H6<2,H6,H6-2) -> 0 | J6: =H6-I6 -> 0 | K6: 0 | L6: 0 | M6: 0 | N6: 0 | O6: 0 | P6: =L6+M6+N6+O6 -> 0 | Q6: =(F6*0.5)+(I6*0.5)+L6+(N6*2)+M6 -> 0 | T6: 0 | U6: =R6-(S6+T6) -> 0 | V6: 7000 | W6: =V6 -> 7000 | X6: 0 | Y6: =V6-AB6 -> 7000 | Z6: =(V6+X6)/31 -> 225.80645 | AA6: =V6*45% -> 3150 | AB6: =Q6*Z6 -> 0 | AD6: =(AC6)*Z6 -> 0 | AE6: =T6 -> 0 | AG6: 0 | AH6: 0 | AI6: =SUM(AB6,AD6:AH6) -> 0 | AJ6: =ROUND(SUM(W6:X6)-AI6,0) -> 7000 | AK6: 0 | AL6: 0 | AN6: 1750060000002123
A7: 3 | B7: AARTHY SELVAM | C7: House Keeping Supervisor | D7: 30 | E7: 0 | F7: =IF((E7/3)>=1,TRUNC(E7/3,0),0) -> 0 | G7: =E7-F7*3 -> 0 | H7: 0 | I7: =IF(H7<1,H7,H7-1) -> 0 | J7: =H7-I7 -> 0 | K7: 0 | L7: 0 | M7: 0 | N7: 0 | O7: 0 | P7: =L7+M7+N7+O7 -> 0 | Q7: =(F7*0.5)+(I7*0.5)+M7+(N7*2) -> 0 | U7: =R7-(S7+T7) -> 0 | V7: 7500 | W7: =V7 -> 7500 | X7: 0 | Y7: =V7-AB7 -> 7500 | Z7: =(V7+X7)/31 -> 241.93548 | AA7: =V7*45% -> 3375 | AB7: =Q7*Z7 -> 0 | AD7: =(AC7)*Z7 -> 0 | AE7: =T7 -> 0 | AF7: 0 | AG7: 0 | AH7: 0 | AI7: =SUM(AB7,AD7:AH7) -> 0 | AJ7: =ROUND(SUM(W7:X7)-AI7,0) -> 7500 | AK7: 0 | AL7: 0 | AN7: 1750060000001274
A8: TOTAL | R8: =SUM(R5:R7) -> 0 | S8: =SUM(S5:S7) -> 0 | T8: =SUM(T5:T7) -> 0 | U8: =SUM(U5:U7) -> 0 | V8: =SUM(V5:V7) -> 40500 | W8: =SUM(W5:W7) -> 40500 | X8: =SUM(X5:X7) -> 0 | Y8: =SUM(Y5:Y7) -> 40500 | ... AL8: =SUM(AL5:AL7) -> 0
A9: HR Manager | V9: Finance Manager | AL9: Director Academics
R15: =(G15*0.5)+(J15*0.5)+N15+(O15*2) -> 0

Sheet ECA 
A1: QUEEN MIRA INTERNATIONAL SCHOOL
A2: ECA REGULAR - SALARY STATEMENT JUNE 2026
A3: ECA Staff - Regular Salary
A4: S.No | B4: Name | C4: Department | D4: Gross Salary | E4: Total No.of Classes | F4: No.of days Leave | G4: Advance Total | H4: Already Paid | I4: Pending Deduction | J4: Current Month deduction | K4: Leave Deduction Amt | L4: Other Deductions | M4: Net Salary | N4: Remarks
A5: 1 | B5: R BALACHANDER | C5: Western Dance | D5: 20000 | E5: 7 | F5: 1 | G5: 0 | I5: 0 | J5: 0 | K5: =D5/8*F5 -> 2500 | L5: 0 | M5: =ROUND(D5-J5-K5-L5,0) -> 17500 | N5: Per day salary calculated= Gross salary / No of classes-Vacation Holiday | O5: 1750060000000106
A6: 2 | B6: ARAVINDHU PASHWAN VELAYUTHAM | C6: Guitar | D6: 12500 | E6: 1 | F6: 1 | G6: 0 | I6: 0 | J6: 0 | K6: =D6/8*F6 -> 1562.5 | L6: 0 | M6: =ROUND(D6-J6-K6-L6,0) -> 10938 | N6: Per day salary calculated= Gross salary / No of classes-Vacation Holiday | O6: 1750061000000241
A7: 3 | B7: J RAJA / Chandra | C7: Silambam | D7: 13000 | E7: 7 | F7: 0 | G7: 0 | I7: 0 | J7: 0 | K7: =D7/8*F7 -> 0 | L7: 0 | M7: =ROUND(D7-J7-K7-L7,0) -> 13000 | N7: Per day salary calculated= Gross salary / No of classes-Vacation Holiday | O7: 1750060000001298
A8: 4 | B8: J RAJA / Amutheswaran | C8: Karate | D8: 12000 | E8: 7 | F8: 0 | G8: 0 | I8: 0 | J8: 0 | K8: =D8/8*F8 -> 0 | L8: 0 | M8: =ROUND(D8-J8-K8-L8,0) -> 12000 | N8: Per day salary calculated= Gross salary / No of classes-Vacation Holiday | O8: 1750060000001298
A9: 5 | B9: PRAKASHKUMAR BALAJI | C9: Taekwondo | D9: 13000 | E9: 7 | F9: 0 | G9: 0 | I9: 0 | J9: 0 | K9: =D9/8*F9 -> 0 | L9: 0 | M9: =ROUND(D9-J9-K9-L9,0) -> 13000 | N9: Per day salary calculated= Gross salary / No of classes-Vacation Holiday - | O9: 1750061000000135
A10: 6 | B10: PRAKASHKUMAR BALAJI | C10: Yoga | D10: 11000 | E10: 8 | F10: 0 | G10: 0 | I10: 0 | J10: 0 | K10: =D10/8*F10 -> 0 | L10: 0 | M10: =ROUND(D10-J10-K10-L10,0) -> 11000 | N10: Per day salary calculated= Gross salary / No of classes-Vacation Holiday | O10: 1750061000000135
A11: 7 | B11: PRABAKARAN PANDI | C11: Kung Fu | D11: 14000 | E11: 7 | F11: 0 | G11: 0 | I11: 0 | J11: 0 | K11: =D11/8*F11 -> 0 | L11: 0 | M11: =ROUND(D11-J11-K11-L11,0) -> 14000 | N11: Per day salary calculated= Gross salary / No of classes-Vacation Holiday | O11: 1750060000000132
A12: 8 | B12: HARIPRASATH JAYAKUMAR | C12: Drums | D12: 12000 | E12: 8 | F12: 0 | G12: 0 | I12: 0 | J12: 0 | K12: =D12/8*F12 -> 0 | L12: 0 | M12: =ROUND(D12-J12-K12-L12,0) -> 12000 | N12: Per day salary calculated= Gross salary / No of classes-Vacation Holiday | O12: 1750061000000265
A13: 9 | B13: RAJA CHINNASAMI | C13: Key Board | D13: 17000 | E13: 8 | F13: 0 | G13: 0 | I13: 0 | J13: 0 | K13: =D13/8*F13 -> 0 | L13: 0 | M13: =ROUND(D13-J13-K13-L13,0) -> 17000 | N13: Per day salary calculated= Gross salary / No of classes-Vacation Holiday | O13: 1750061000000232
A14: 10 | B14: JEYA SHREE R | C14: Classical Dance | D14: 20500 | E14: 8 | F14: 0 | G14: 0 | I14: 0 | J14: 0 | K14: =D14/8*F14 -> 0 | L14: 0 | M14: =ROUND(D14-J14-K14-L14,0) -> 20500 | N14: Per day salary calculated= Gross salary / No of classes-Vacation Holiday | O14: 1750060000000850
A15: 11 | B15: SUBAHARI | C15: Carnatic Music | D15: 18000 | E15: 8 | F15: 0 | G15: 0 | I15: 0 | J15: 0 | K15: =D15/8*F15 -> 0 | L15: 0 | M15: =ROUND(D15-J15-K15-L15,0) -> 18000 | N15: Per day salary calculated= Gross salary / No of classes-Vacation Holiday | O15: 1750061000000253
A16: 12 | B16: DANIEL MERWIN SELVARAJ | C16: Skatting Coach | D16: 26000 | E16: 19 | F16: 0 | G16: 0 | I16: 0 | J16: 0 | K16: =D16/31*F16 -> 0 | L16: 0 | M16: =ROUND(D16-J16-K16-L16,0) -> 26000 | N16: Per day salary calculated= Gross salary / No of days 30 or 31-Vacation Holiday | O16: 1750061000000289
A17: 13 | B17: K KEERTHIGA | C17: Arts and Craft | D17: 12000 | E17: 6 | F17: 1 | G17: 0 | I17: 0 | J17: 0 | K17: =D17/31*F17 -> 387.09677 | L17: 0 | M17: =ROUND(D17-J17-K17-L17,0) -> 11613 | N17: No salary for April'2026 - No classes assigned. Per day salary calculated= Gross salary / No of days 30 or 31-Vacation Holiday | O17: '1750060000001300
A18: 14 | B18: ARUNKANTH MURUGAN | C18: Table Tennis | D18: 20000 | E18: 18 | F18: 0 | G18: 0 | I18: 0 | J18: 0 | K18: =D18/31*F18 -> 0 | L18: 0 | M18: =ROUND(D18-J18-K18-L18,0) -> 20000 | N18: Per day salary calculated= Gross salary / No of days 30 or 31-Vacation Holiday | O18: 1750061000000348
A19: Total | D19: =SUM(D5:D18) -> 221000 | E19: =SUM(E5:E18) -> 119 | F19: =SUM(F5:F18) -> 3 | G19: =SUM(G5:G18) -> 0 | H19: =SUM(H5:H18) -> 0 | I19: =SUM(I5:I18) -> 0 | J19: =SUM(J5:J18) -> 0 | K19: =SUM(K5:K18) -> 4449.5968 | ... M19: =SUM(M5:M18) -> 216551 | XFD19: =SUM(D19:XFC19) -> 442122.6
A20: HR Manager Finance Manager Director Academics

Sheet Part time academic
A1: QUEEN MIRA INTERNATIONAL SCHOOL
A2: Part Time Academics - SALARY STATEMENT JUNE 2026
A3: S.No | B3: Name | C3: Department | D3: Gross Salary | E3: Classes taken / Days reported | F3: Per Day Salary | G3: No. of Leaves | H3: Special Deductions | I3: Leave Deductions | J3: Net Salary | K3: Remarks
A4: 1 | B4: Chandrashekaran | C4: Chemistry | D4: =E4*1600 -> 57600 | E4: 36 | F4: =D4/30 -> 1920 | G4: 0 | H4: 0 | I4: =F4*G4 -> 0 | J4: =ROUND(D4-I4-H4,0) -> 57600 | K4: 1600 Per hour. / Due to Emergncy Salary Given on 30/06/2026(54000) | L4: Cash
A5: 3 | B5: Thirubuvan | C5: Physics | D5: =E5*1200 -> 44592 | E5: 37.16 | F5: =D5/30 -> 1486.4 | G5: 0 | H5: 0 | I5: =F5*G5 -> 0 | J5: =ROUND(D5-I5-H5,0) -> 44592 | K5: 1200 Per hour. | L5: 1750061000000419
A6: 4 | B6: Naveen Kumar | C6: French | D6: =20000 -> 20000 | E6: 20 | F6: =D6/30 -> 666.66667 | G6: 1 | I6: =F6*G6 -> 666.66667 | J6: =ROUND(D6-I6-H6,0) -> 19333 | K6: Leave on 17/06/2026 | L6: 1750060000001215
A7: 5 | B7: KALPANA KARTHIK S | C7: Curriculum Advisor & PGT Economics | D7: 36000 | E7: 27 | F7: =D7/30 -> 1200 | I7: =F7*G7 -> 0 | J7: =ROUND(D7-I7-H7,0) -> 36000 | K7: Gross Salary Rs. 36,000. she worked Full day on 13/06/2026 ,15/06/2026, 20/06/2026,22/06/2026, 29/06/2026 | L7: 1750062000000034
A8: 6 | B8: MATCHIPIRAI MALIKA KATHEROLI | C8: Hindi | D8: 44000 | E8: 30 | F8: =D8/30 -> 1466.6667 | G8: 0 | I8: =F8*G8 -> 0 | J8: =ROUND(D8-I8-H8,0) -> 44000 | L8: 1750061000000312
A9: 7 | B9: I PRADEEP CHRISTOPHER | C9: French | D9: 29000 | E9: 12 | F9: =D9/30 -> 966.66667 | I9: =F9*G9 -> 0 | J9: =ROUND(D9-I9-H9,0) -> 29000 | L9: 1750061000000362
A10: 8 | B10: DHARANI W/O SRINIVAS | C10: School Counsellor | D10: 46000 | E10: 11 | F10: =D10/30 -> 1533.3333 | I10: =F10*G10 -> 0 | J10: =ROUND(D10-I10-H10,0) -> 46000 | L10: 1750061000000220
A11: 9 | B11: Jeyabal J | C11: Creative space | D11: =450*E11 -> 2700 | E11: 6 | F11: =D11/30 -> 90 | G11: 0 | I11: =F11*G11 -> 0 | J11: =ROUND(D11-I11-H11,0) -> 2700 | K11: (Actual classes to be planned 8 days * 8 periods = 64 periods for each) Per period Rs 450 No Class in April 2026 | L11: 1105155000093166
A12: 11 | B12: Niveth Oliviya | C12: Creative space | D12: =450*E12 -> 0 | E12: 0 | F12: =D12/30 -> 0 | G12: 0 | I12: =F12*G12 -> 0 | J12: =ROUND(D12-I12-H12,0) -> 0 | L12: 1750060000001203
A13: 12 | B13: Anushkumar | C13: Creative space Tuesday and Friday | D13: =20000/9*3 -> 6666.6667 | E13: 2 | F13: =D13/9 -> 740.74074 | G13: 0 | I13: =F13*G13 -> 0 | J13: =ROUND(D13-I13-H13,0) -> 6667 | K13: DOJ 23/06/26 / 1 Holiday
A14: Total | D14: =SUM(D4:D13) -> 286558.67 | E14: =SUM(E4:E13) -> 181.16 | F14: =SUM(F4:F12) -> 9329.7333 | G14: =SUM(G4:G12) -> 1 | H14: =SUM(H4:H12) -> 0 | I14: =SUM(I4:I12) -> 666.66667 | J14: =SUM(J4:J12) -> 279225
A15: HR Manager | E15: Finance Manager | K15: Director Academics

Sheet Theni - Upparpatti
A1: QUEEN MIRA INTERNATIONAL SCHOOL
A2: THENI UPPARPATTI - SALARY STATEMENT JUNE 2026
A3: S.No | B3: Name | C3: Department | D3: Attendance | R3: Salary Advance / Loan Details | V3: Gross Salary | W3: Payable Gross Salary | X3: Other Allownace | Y3: Salary.Actuals [Gross Salary - Leave Deduction] | Z3: Salary per day [Gross salary / no of days that month] | AA3: Basic [45% of Gross Salary] | AB3: Deductions | AJ3: Net Salary | AK3: QMIS Contribution | AM3: Remarks
D4: Total working days | E4: Lates. Actuals | F4: Lates. Leave [Exceeding lates conversions count] | G4: Final Lates after deducting exceeding Late leaves | H4: Permissions.Actuals | I4: Exceeding Permissions taken for this month | J4: Proper Permissions | K4: Proper Casual Leave already taken for this term | L4: Proper Casual Leave already taken for this year till date | M4: Exceeding Casual Leave taken for this month / Memo issued | N4: Absent / Suspension.Actuals | O4: Gardening / Other Leave | P4: Total Leave days.Actuals | Q4: Loss of Pay Days | R4: Total Loan Amount | S4: Amount already paid | T4: Amount to be paid for this month | U4: Remaining Loan Amount | AB4: Leave / Absent / Permission Leave / Late Leave | AC4: Not Punched Days | AD4: Not Punched LOP | AE4: Salary Advance / Loan | AF4: Special Deductions [Telephone Bill + Laptop + Uniform + Trainings etc] | AG4: PF [12% of Basic Salary] | AH4: ESI [0.75% of Salary.Actuals] | AI4: Total | AK4: PF [13.01% of Basic Salary] | AL4: ESI [3.25% of Salary.Actuals]
A5: 1 | B5: SUJATHA D/O SUBBURAM | C5: Director Academics | D5: 30 | E5: 0 | F5: =IF((E5/3)>=1,TRUNC(E5/3,0),0) -> 0 | G5: =E5-F5*3 -> 0 | H5: 0 | I5: =IF(H5<1,H5,H5-1) -> 0 | J5: =H5-I5 -> 0 | K5: 0 | L5: 0 | M5: 0 | N5: 0 | O5: 0 | P5: =L5+M5+N5+O5 -> 0 | Q5: =(F5*0.5)+(I5*0.5)+M5+(N5*2) -> 0 | U5: =R5-(S5+T5) -> 0 | V5: 10000 | W5: =V5 -> 10000 | X5: 0 | Y5: =V5-AB5 -> 10000 | Z5: =V5/D5 -> 333.33333 | AA5: =V5*45% -> 4500 | AB5: =Q5*Z5 -> 0 | AD5: =(AC5)*Z5 -> 0 | AE5: =T5 -> 0 | AG5: 0 | AH5: 0 | AI5: =SUM(AB5:AH5) -> 0 | AJ5: =ROUND(SUM(W5:X5)-AI5,) -> 10000 | AN5: 1750063000000016
A6: 2 | B6: JOSEPHINE ANNE SHEEBHA ARULDASS | C6: Joint director Admin | D6: 30 | E6: 0 | F6: =IF((E6/3)>=1,TRUNC(E6/3,0),0) -> 0 | G6: =E6-F6*3 -> 0 | H6: 0 | I6: =IF(H6<1,H6,H6-1) -> 0 | J6: =H6-I6 -> 0 | K6: 0 | L6: 0 | M6: 0 | N6: 0 | O6: 0 | P6: =L6+M6+N6+O6 -> 0 | Q6: =(F6*0.5)+(I6*0.5)+M6+(N6*2) -> 0 | U6: =R6-(S6+T6) -> 0 | V6: 10000 | W6: =V6 -> 10000 | X6: 0 | Y6: =V6-AB6 -> 10000 | Z6: =V6/D6 -> 333.33333 | AA6: =V6*45% -> 4500 | AB6: =Q6*Z6 -> 0 | AD6: =(AC6)*Z6 -> 0 | AE6: =T6 -> 0 | AG6: 0 | AH6: 0 | AI6: =SUM(AB6:AH6) -> 0 | AJ6: =ROUND(SUM(W6:X6)-AI6,) -> 10000 | AN6: 1750060000002726
A7: TOTAL | R7: =SUM(R5:R6) -> 0 | S7: =SUM(S5:S6) -> 0 | T7: =SUM(T5:T6) -> 0 | U7: =SUM(U5:U6) -> 0 | V7: =SUM(V5:V6) -> 20000 | W7: =SUM(W5:W6) -> 20000 | X7: =SUM(X5:X6) -> 0 | Y7: =SUM(Y5:Y6) -> 20000 | ... AL7: =SUM(AL5:AL6) -> 0
A8: HR Manager | U8: Finance Manager | AK8: Joint Director Admin

Sheet AEP
A1: P
A2: AEP - SALARY STATEMENT JUNE 2026
A3: S.No | B3: Name | C3: Department | D3: Gross Salary | E3: Total Hours Taken | F3: Other Deduction | G3: Leave Deductions | H3: Conveyance Allowance | I3: Net Salary | J3: Remarks
A4: 1 | B4: Sudha | C4: Biology | D4: =E4*1200 -> 0 | E4: 0 | G4: 0 | H4: =0*750 -> 0 | I4: =ROUND((D4+H4)-G4,0) -> 0 | J4: Per hour 1200 + Conveyance allowance Per day 750. No classes taken | K4: 1750061000000383
A5: 2 | B5: Thiribuvan | C5: Physics | D5: =E5*1050 -> 0 | E5: 0 | G5: 0 | I5: =ROUND((D5+H5)-G5,0) -> 0 | J5: Per hour 1050 No classes taken | K5: 1750061000000419
A6: Total | D6: =SUM(D4:D5) -> 0 | E6: =SUM(E4:E5) -> 0 | F6: =SUM(F4:F5) -> 0 | G6: =SUM(G4:G5) -> 0 | H6: =SUM(H4:H5) -> 0 | I6: =SUM(I4:I5) -> 0
A7: HR Manager Finance Manager Director Academics

Sheet Rifle
A1: QUEEN MIRA INTERNATIONAL SCHOOL
A2: RIFLE SHOOTING - SALARY STATEMENT JUNE 2026
A3: S.No | B3: Name | C3: Department | D3: Gross Salary | E3: Classes Taken | F3: Special Deduction | G3: Advance Total | H3: Advance Deduction | I3: To be Deducted | J3: Leave / other Deductions | K3: Total Deductions | L3: Net Salary | M3: Remarks
A4: 1 | B4: Kumar | C4: Rifle | D4: 66000 | E4: 7 | F4: 0 | G4: 0 | H4: 0 | I4: 0 | K4: =F4++H4+J4 -> 0 | L4: =D4-K4 -> 66000 | M4: June '2026 Salary paid in May 2026 Statement.
A5: Total | D5: =SUM(D4) -> 66000 | E5: =SUM(E4) -> 7 | F5: =SUM(F4) -> 0 | G5: =SUM(G4) -> 0 | H5: =SUM(H4) -> 0 | I5: =SUM(I4) -> 0 | J5: =SUM(J4) -> 0 | K5: =SUM(K4) -> 0 | L5: =SUM(L4) -> 66000
A6: HR Manager | H6: Finance Manager | M6: Director Academics

Sheet Part Time - Admin
A1: QUEEN MIRA INTERNATIONAL SCHOOL
A2: ADMIN PART TIME - SALARY STATEMENT JUNE 2026
A3: S.No | B3: Name | C3: Department | D3: Gross Salary | E3: Other Allowance | F3: No. of Days Present | G3: Per Day Salary | H3: Advance Total | I3: Advance Deduction | J3: No. Of Leaves | K3: Other Deduction | L3: Leave Deductions | M3: Total Deductions | N3: Net Salary | O3: Remarks
A4: 1 | B4: M Vijay | C4: Assistant - Public Relations Officer | D4: =((18800+1880)+3000)/31*F4 -> 0 | F4: 0 | G4: =((18800+1880)+3000)/31 -> 763.87097 | H4: 0 | I4: 0 | J4: 0 | K4: 0 | L4: =G4*J4 -> 0 | M4: =I4+L4+K4 -> 0 | N4: =ROUND(D4-M4,0) -> 0 | O4: As per MD's instruction, salary will be paid based on the no. of working days which will be given by Mr. Sounder and it should be acknowledged by Ms Sivaranjani. Not reported | P4: Cash
A5: 2 | B5: Dr Beena | C5: L & OD Consultant | D5: =35000 -> 35000 | F5: 8 | G5: =D5/31 -> 1129.0323 | H5: 0 | I5: 0 | J5: 0 | K5: 0 | L5: =G5*J5 -> 0 | M5: =I5+L5+K5 -> 0 | N5: =ROUND(D5-M5,0) -> 35000 | O5: Salary revised from Rs 45,000 to Rs, 35,000 | P5: Cash
A6: Total | D6: =SUM(D4:D5) -> 35000 | E6: =SUM(E4:E5) -> 0 | F6: =SUM(F4:F5) -> 8 | G6: =SUM(G4:G5) -> 1892.9032 | H6: =SUM(H4:H5) -> 0 | I6: =SUM(I4:I5) -> 0 | J6: =SUM(J4:J5) -> 0 | K6: =SUM(K4:K5) -> 0 | ... N6: =SUM(N4:N5) -> 35000
A7: HR Manager | N7: Finance Manager

Sheet Sheet5
A1: Account No. | B1: Customer Name
B2: UMA MAHESWARI NAGARAJAN
B3: KALAIYARASI M
B4: GURUVAMMAL RAVI
B5: MARIYAMMAL B
B6: SUNDARI JEYARAM
B7: MURUGESHWARI PANDYARAJA
B8: KALPANA S
B9: GNANAMANI SANKARALINGAM
B10: VIJI TAMILSELVAN
B11: POTHUPONNU K | D11: 1750059000000208 | E11: JAYA DHINAKARAN
B12: JOY SHEEBA A | D12: 1750059000000290 | E12: S THASNEEM
B13: AKILANDESWARI SHANMUGANATHAN | D13: 1750059000000326 | E13: MALLIKA
B14: BHUVANESWARI RAMPRABU | E14: PORKALAISELVI SENTHILKUMAR
B15: SASIREKHA M | D15: 1750060000000200 | E15: RAJASEKARAN SHANMUGAM
B16: SILAMBARASI J | D16: 1750060000000248 | E16: R POOJA
B17: S VINODHINI | D17: 1750060000000262 | E17: KANIMOZHI G
B18: UMA I . | D18: 1750060000000295 | E18: JABESTIN THAMAS YAKGOPU
B19: GOVINDAMMAL SIVAKUMAR | D19: 1750060000000321 | E19: NAGARANI M
B20: VAIRAMANI BOSE | D20: 1750060000000354 | E20: M VASANTHI
B21: R SUTHA | D21: 1750060000000378 | E21: BALAMANI R
B22: K BALASARAVANAN | D22: 1750060000000401 | E22: VIDHYA VEERAPANDIAN
B23: PARVATHI M | D23: 1750060000000661 | E23: SANGEETHA R
B24: UMARANI T | D24: 1750060000000673 | E24: PREMKUMAR MURUGESAN
B25: JEYALAKSHMI M | D25: 1750060000000685 | E25: MARIYA VISUVASAM A
B26: VIJAYA CHELLAPANDI | D26: 1750060000000898 | E26: VIJAY
... B29: KALEESWARI | D29: 1750060000001111 | E29: MUTHUKALEESWARAN R
B30: PALANIYAMMAL
B31: ANGALAESWRI
B32: ASSWAH R
B33: DEEPIKA KANNAN
B34: VIJAYALAKSHMI
B35: KANNAN BALAKRISHNAN
B36: MUTHUKUMAR J
B37: JOY JEBA SUNDARY
B38: JAYANTHI
B39: P Meenakshi
B40: PEAR MORRISH N
B41: SHALINI JOSEPH MANOHARAN
... B125: RAMESH KUMAR R
A126: 1750060000000992 | B126: JOHN
B127: R BALACHANDER
B128: VARATHARAJAN
B129: ANUSUYA S
B130: SWARNAMATHI
B131: ANCHANA
B132: AYYANAR
B133: KARTHIGA
B134: DIVYA LENIN
B135: NIVETH
B136: NAVEENKUMAR
B137: SANGEETHA M S T
B138: KAVITHA A
... B186: SUJATHA SUBBURAM

Sheet Sheet6
B2: May | C2: April | H2: April
B3: Gross Salary | C3: Gross Salary | G3: Gross Salary | H3: Gross Salary
B5: 105000 | C5: 105000 | D5: =+B5-C5 -> 0 | G5: 85000 | H5: 85000 | I5: =+G5-H5 -> 0
B6: 36000 | C6: 36000 | D6: =+B6-C6 -> 0 | G6: 25000 | H6: 25000 | I6: =+G6-H6 -> 0
B7: 34500 | C7: 34500 | D7: =+B7-C7 -> 0 | G7: 75000 | H7: 75000 | I7: =+G7-H7 -> 0
B8: 23000 | C8: 23000 | D8: =+B8-C8 -> 0 | G8: 32000 | H8: 32000 | I8: =+G8-H8 -> 0
B9: 21000 | C9: 21000 | D9: =+B9-C9 -> 0 | G9: 34000 | H9: 34000 | I9: =+G9-H9 -> 0
B10: 70000 | C10: 70000 | D10: =+B10-C10 -> 0 | G10: 20000 | H10: 20000 | I10: =+G10-H10 -> 0
B11: 30000 | C11: 30000 | D11: =+B11-C11 -> 0 | G11: 16200 | H11: 16200 | I11: =+G11-H11 -> 0
B12: 27000 | C12: 27000 | D12: =+B12-C12 -> 0 | G12: 14900 | H12: 14900 | I12: =+G12-H12 -> 0
B13: 39000 | C13: 39000 | D13: =+B13-C13 -> 0 | H13: 24000 | I13: =+G13-H13 -> -24000
B14: 21500 | C14: 21500 | D14: =+B14-C14 -> 0 | G14: 27000 | H14: 27000 | I14: =+G14-H14 -> 0
B15: 48500 | C15: 48500 | D15: =+B15-C15 -> 0 | G15: 20000 | H15: 20000 | I15: =+G15-H15 -> 0
B16: 60000 | C16: 60000 | D16: =+B16-C16 -> 0 | G16: 15200 | H16: 15200 | I16: =+G16-H16 -> 0
B17: 37000 | C17: 37000 | D17: =+B17-C17 -> 0 | G17: 33000 | H17: 33000 | I17: =+G17-H17 -> 0
B18: 45000 | C18: 45000 | D18: =+B18-C18 -> 0 | G18: 15000 | H18: 15000 | I18: =+G18-H18 -> 0
B19: 36000 | C19: 36000 | D19: =+B19-C19 -> 0 | G19: 43000 | H19: 43000 | I19: =+G19-H19 -> 0
B20: 27000 | C20: 27000 | D20: =+B20-C20 -> 0 | G20: 24000 | H20: 24000 | I20: =+G20-H20 -> 0
B21: 56000 | C21: 56000 | D21: =+B21-C21 -> 0 | G21: 16900 | H21: 16900 | I21: =+G21-H21 -> 0
B22: 52000 | C22: 52000 | D22: =+B22-C22 -> 0 | G22: 60000 | H22: 60000 | I22: =+G22-H22 -> 0
B23: 45000 | C23: 45000 | D23: =+B23-C23 -> 0 | G23: 65000 | H23: 65000 | I23: =+G23-H23 -> 0
B24: 29000 | C24: 29000 | D24: =+B24-C24 -> 0 | G24: 23000 | H24: 23000 | I24: =+G24-H24 -> 0
B25: 44000 | C25: 44000 | D25: =+B25-C25 -> 0 | G25: 24800 | H25: 24800 | I25: =+G25-H25 -> 0
... B29: 30000 | C29: 30000 | D29: =+B29-C29 -> 0 | G29: 14000 | H29: 14000 | I29: =+G29-H29 -> 0
C30: 34000 | D30: =+B30-C30 -> -34000 | G30: 25000 | H30: 25000 | I30: =+G30-H30 -> 0
B31: 29000 | C31: 29000 | D31: =+B31-C31 -> 0 | G31: 30000 | H31: 30000 | I31: =+G31-H31 -> 0
B32: 30500 | C32: 30500 | D32: =+B32-C32 -> 0 | G32: 20000 | H32: 20000 | I32: =+G32-H32 -> 0
B33: 27000 | C33: 27000 | D33: =+B33-C33 -> 0 | G33: 20000 | H33: 20000 | I33: =+G33-H33 -> 0
B34: 18000 | C34: 18000 | D34: =+B34-C34 -> 0 | G34: 21000 | H34: 21000 | I34: =+G34-H34 -> 0
B35: 20000 | C35: 20000 | D35: =+B35-C35 -> 0 | G35: 30000 | H35: 30000 | I35: =+G35-H35 -> 0
C36: 34000 | D36: =+B36-C36 -> -34000 | G36: 25000 | H36: 25000 | I36: =+G36-H36 -> 0
B37: 23500 | C37: 23500 | D37: =+B37-C37 -> 0 | G37: 20000 | H37: 20000 | I37: =+G37-H37 -> 0
B38: 30000 | C38: 30000 | D38: =+B38-C38 -> 0 | G38: 16000 | H38: 16000 | I38: =+G38-H38 -> 0
B39: 17500 | C39: 17500 | D39: =+B39-C39 -> 0 | G39: 15000 | H39: 15000 | I39: =+G39-H39 -> 0
B40: 22000 | C40: 22000 | D40: =+B40-C40 -> 0 | G40: 16500 | H40: 16500 | I40: =+G40-H40 -> 0
B41: 16000 | C41: 16000 | D41: =+B41-C41 -> 0 | G41: 25000 | H41: 25000 | I41: =+G41-H41 -> 0
B42: 44000 | C42: 44000 | D42: =+B42-C42 -> 0 | G42: 15000 | H42: 15000 | I42: =+G42-H42 -> 0
B43: 26500 | C43: 26500 | D43: =+B43-C43 -> 0 | G43: 18000 | H43: 18000 | I43: =+G43-H43 -> 0
B44: 12600 | C44: 12600 | D44: =+B44-C44 -> 0 | G44: 15000 | H44: 15000 | I44: =+G44-H44 -> 0
B45: 25000 | C45: 25000 | D45: =+B45-C45 -> 0 | G45: 14000 | H45: 14000 | I45: =+G45-H45 -> 0
B46: 27000 | C46: 27000 | D46: =+B46-C46 -> 0 | G46: 14000 | H46: 14000 | I46: =+G46-H46 -> 0
B47: 24000 | C47: 24000 | D47: =+B47-C47 -> 0 | G47: 13000 | H47: 13000 | I47: =+G47-H47 -> 0
B48: 22000 | C48: 22000 | D48: =+B48-C48 -> 0 | G48: 18000 | H48: 18000 | I48: =+G48-H48 -> 0
B49: 25000 | C49: 25000 | D49: =+B49-C49 -> 0 | G49: 12000 | H49: 12000 | I49: =+G49-H49 -> 0
B50: 23000 | C50: 23000 | D50: =+B50-C50 -> 0 | G50: =SUM(G5:G49) -> 1115500 | H50: =SUM(H5:H49) -> 1139500
B51: 20000 | C51: 20000 | D51: =+B51-C51 -> 0
C52: 30000 | D52: =+B52-C52 -> -30000
B53: 16000 | C53: 16000 | D53: =+B53-C53 -> 0
B54: 24000 | C54: 24000 | D54: =+B54-C54 -> 0
B55: 24000 | C55: 24000 | D55: =+B55-C55 -> 0
B56: 25000 | C56: 25000 | D56: =+B56-C56 -> 0
C57: 23000 | D57: =+B57-C57 -> -23000
B58: 25000 | C58: 25000 | D58: =+B58-C58 -> 0
B59: 25000 | C59: 25000 | D59: =+B59-C59 -> 0
B60: 25000 | C60: 25000 | D60: =+B60-C60 -> 0
B61: 70000 | C61: 70000 | D61: =+B61-C61 -> 0
B62: 17000 | C62: 17000 | D62: =+B62-C62 -> 0
B63: 13000 | C63: 13000 | D63: =+B63-C63 -> 0
B64: 16000 | C64: 16000 | D64: =+B64-C64 -> 0
B65: 27000 | C65: 27000 | D65: =+B65-C65 -> 0
B66: 15000 | C66: 15000 | D66: =+B66-C66 -> 0
B67: 25000 | C67: 25000 | D67: =+B67-C67 -> 0
B68: 60000 | C68: 60000 | D68: =+B68-C68 -> 0
B69: 30000 | C69: 30000 | D69: =+B69-C69 -> 0
B70: =20000 -> 20000 | C70: =20000 -> 20000 | D70: =+B70-C70 -> 0
B71: 45000 | C71: 45000 | D71: =+B71-C71 -> 0
B72: 22000 | C72: 22000 | D72: =+B72-C72 -> 0
B73: 34000 | C73: 34000 | D73: =+B73-C73 -> 0
B74: 40000 | C74: 40000 | D74: =+B74-C74 -> 0
B75: 50000 | C75: 50000 | D75: =+B75-C75 -> 0
B76: 15000 | C76: 15000 | D76: =+B76-C76 -> 0
B77: 18000 | C77: 18000 | D77: =+B77-C77 -> 0
B78: 30000 | C78: =SUM(C5:C77) -> 2252100 | D78: =+B78-C78 -> -2222100
B79: 23000 | D79: =+B79-C79 -> 23000
B80: 22000 | D80: =+B80-C80 -> 22000
B81: =SUM(B5:B80) -> 2206100 | D81: =+B82-C81 -> 0

Sheet Sheet2
B2: SALARY CHECKLIST | E2: 1 | F2: Action plan
B3: S.No | C3: Category | E3: 2 | F3: Prime And Suspense
B4: 1 | C4: Action plan | D4: Check Account Number | E4: 3 | F4: Attendance closure
B5: 2 | C5: Prime And Suspense | D5: Check Other bank account number | E5: 4 | F5: ECA I - Uma Maheswaran
B6: 3 | C6: 2 Months Comparison | D6: uniform | E6: 5 | F6: ECA II - Indira
B7: 4 | C7: 3 Months Comparison | D7: Shoe | E7: 6 | F7: AEP - Joe Daniel and Vanitha and Sangamithra
B8: 5 | C8: Ms. Ashrafa acknowledgement | E8: 7 | F8: Comp off details - Parthiban, joe daniel, Bala
B9: 6 | C9: MD, DA & JD-Admin Discretion | E9: 8 | F9: Ms Christinal - Parthiban
B10: 7 | C10: Security OT | E10: 9 | F10: Salary advance to be check
B11: 8 | C11: Salary Statement | E11: 10 | F11: Uniform pending amount
B12: 9 | C12: Gold scheme | E12: 11 | F12: Memo, suspension deduction
B13: 10 | C13: Chit Fund Details | E13: 12 | F13: Gold scheme
B14: 11 | C14: Cheque Signing | E14: 13 | F14: Cheque to be collected for finance department
E15: 14 | F15: PF and ESI
F16: Chit Fund deduction

Sheet Split Up
B3: Salary Split - Up
B4: Salary for the month of May 2026
B5: S.No | C5: Particulars | D5: Salary | E5: Actual Salary | F5: Difference
B6: 1 | C6: Teaching | D6: =+Academics!AJ7+'Relieved Academics'!AJ8-10000-13548-2226-2129 -> 121625 | E6: =D6 -> 121625 | F6: =D6-E6 -> 0
B7: 2 | C7: Admin | D7: =+Admin!AJ7+'Relieved Admin'!#REF!-25000-75000-5000 -> #REF! | E7: =D7 -> #REF! | F7: =D7-E7 -> #REF!
B8: 3 | C8: Support | D8: =+Drivers!AJ7+Conductors!AJ7+Securities!AJ7+'House Keeping'!AJ7-11924-2258-1581-13548-8581-6774 -> 76033 | E8: =D8 -> 76033 | F8: =D8-E8 -> 0
B9: 4 | C9: Hostel | D9: =+Hostel!AJ8 -> 40500 | E9: =D9 -> 40500 | F9: =D9-E9 -> 0
B10: 5 | C10: AEP | D10: =+AEP!I6 -> 0 | E10: =D10 -> 0 | F10: =D10-E10 -> 0
B11: 6 | C11: Theni - Upparpatti | D11: =+'Theni - Upparpatti'!AJ7-20000 -> 0 | E11: =D11 -> 0 | F11: =D11-E11 -> 0
B12: 7 | C12: ECA | D12: =+'Part time academic'!J14-18000 -> 261225 | E12: =D12 -> 261225 | F12: =D12-E12 -> 0
B13: 8 | C13: Management | D13: 45000 | E13: 25000 | F13: =D13-E13 -> 20000
B14: 9 | C14: NEFT-NT/ECA | D14: =11924+75000 -> 86924 | E14: =D14 -> 86924 | F14: =D14-E14 -> 0
B15: 10 | C15: Rifle | D15: =+Rifle!L5 -> 66000 | E15: =D15 -> 66000 | F15: =D15-E15 -> 0
B16: 11 | C16: Cash | D16: =+'Part Time - Admin'!N6+18000+10000+13548+2226+2129+2258+1581+13548+8581+5000+20000+6774 -> 138645 | E16: =D16 -> 138645 | F16: =D16-E16 -> 0
B17: Total | D17: =SUM(D6:D16) -> #REF! | E17: =SUM(E6:E16) -> #REF! | F17: =SUM(F6:F16) -> #REF!
C20: Cheque Amount | D20: =+D17-D16 -> #REF!
C21: Actual Salary | D21: =+E17 -> #REF!
C22: Difference | D22: =+D21-D20 -> #REF!
C24: Salary | D24: =D17 -> #REF! | E24: EPF | F24: =+'Overall - Top sheet'!J20+'Overall - Top sheet'!M20 -> 17310
C25: Actual Salary | D25: =E17 -> #REF! | E25: ESI | F25: =+'Overall - Top sheet'!K20+'Overall - Top sheet'!N20 -> 2548
C26: Difference | D26: =D24-D25 -> #REF! | E26: Aristo | F26: 12000

Sheet Sheet1
E3: Teaching | F3: Admin | G3: Hostel | H3: Support | I3: Theni | J3: AEP | K3: ECA | L3: Management | M3: ECA NEFT | N3: Rifle | O3: Cash | P3: Total
E4: ='Split Up'!D6 -> 121625 | F4: ='Split Up'!D7 -> #REF! | G4: ='Split Up'!D9 -> 40500 | H4: ='Split Up'!D8 -> 76033 | I4: ='Split Up'!D11 -> 0 | J4: ='Split Up'!D10 -> 0 | K4: ='Split Up'!D12 -> 261225 | L4: ='Split Up'!D13 -> 45000 | M4: ='Split Up'!D14 -> 86924 | N4: ='Split Up'!D15 -> 66000 | O4: ='Split Up'!D16 -> 138645 | P4: =SUM(E4:O4) -> #REF!
D5: KVB | E5: =E4-SUM(E6:E34) -> 70560 | F5: =F4-SUM(F6:F34) -> #REF! | G5: =G4-SUM(G6:G34) -> 40500 | H5: =H4-SUM(H6:H34) -> 76033 | I5: =I4-SUM(I6:I34) -> 0 | J5: =J4-SUM(J6:J34) -> 0 | K5: =K4-SUM(K6:K34) -> 261225 | P5: =SUM(E5:O5) -> #REF!
P6: =SUM(E6:O6) -> 0
D7: Kavitha | E7: 28065 | P7: =SUM(E7:O7) -> 28065
D8: Joy jeba | E8: 23000 | P8: =SUM(E8:O8) -> 23000
D9: Aadhil | F9: 43000 | P9: =SUM(E9:O9) -> 43000
D10: Sivaranjani | F10: 8770 | P10: =SUM(E10:O10) -> 8770
P11: =SUM(E11:O11) -> 0
D12: Aarthi T | F12: 20000 | P12: =SUM(E12:O12) -> 20000
D13: Sakthivel | F13: 20261 | P13: =SUM(E13:O13) -> 20261
D14: Shanmugavalli | F14: 18500 | P14: =SUM(E14:O14) -> 18500
D15: Morrish | F15: 13177 | P15: =SUM(E15:O15) -> 13177
D16: Martin | F16: 10758 | P16: =SUM(E16:O16) -> 10758
P17: =SUM(E17:O17) -> 0
D18: Sathis | F18: 23226 | P18: =SUM(E18:O18) -> 23226
D19: Pradeep | F19: 16500 | P19: =SUM(E19:O19) -> 16500
D20: Kaushik | F20: 13355 | P20: =SUM(E20:O20) -> 13355
P21: =SUM(E21:O21) -> 0
D22: Sathis | M22: 11924 | P22: =SUM(E22:O22) -> 11924
D23: Shalini | F23: 24636 | P23: =SUM(E23:O23) -> 24636
D24: Aarthi selvam | F24: 4265 | P24: =SUM(E24:O24) -> 4265
D25: Karthic T | F25: 21403 | P25: =SUM(E25:O25) -> 21403
D26: Ilamathi | F26: 25258 | P26: =SUM(E26:O26) -> 25258
D27: Ashrafa | M27: 75000 | P27: =SUM(E27:O27) -> 75000
D28: Deepika | F28: 18387 | P28: =SUM(E28:O28) -> 18387
D29: Janani | F29: 25542 | P29: =SUM(E29:O29) -> 25542
D30: KeerthanA | F30: 30000 | P30: =SUM(E30:O30) -> 30000
D31: Management | L31: 45000 | P31: =SUM(E31:O31) -> 45000
D32: Rifle | N32: 60000 | P32: =SUM(E32:O32) -> 60000
D33: Cash | O33: =+'Split Up'!D16 -> 138645 | P33: =SUM(E33:O33) -> 138645
P34: =SUM(E34:O34) -> 0
D36: Total | E36: =SUM(E5:E35) -> 121625 | F36: =SUM(F5:F35) -> #REF! | G36: =SUM(G5:G35) -> 40500 | H36: =SUM(H5:H35) -> 76033 | I36: =SUM(I5:I35) -> 0 | J36: =SUM(J5:J35) -> 0 | K36: =SUM(K5:K35) -> 261225 | L36: =SUM(L5:L35) -> 45000 | ... P36: =SUM(P5:P35) -> #REF!
D38: Difference | E38: =E4-E36 -> 0 | F38: =F4-F36 -> #REF! | G38: =G4-G36 -> 0 | H38: =H4-H36 -> 0 | I38: =I4-I36 -> 0 | J38: =J4-J36 -> 0 | K38: =K4-K36 -> 0 | L38: =L4-L36 -> 0 | ... P38: =P4-P36 -> #REF!
D41: Teaching | E41: 1962120 | F41: =10000+10000 -> 20000 | G41: 12581 | H41: =E41-F41+G41 -> 1954701
D42: Non Teaching | E42: 877178 | F42: 140007 | G42: 9194 | H42: =E42-F42+G42 -> 746365
D43: Hostel | E43: 15663 | H43: =E43-F43+G43 -> 15663
D44: Drivers | E44: =206981+79738+92187+140134 -> 519040 | F44: =13576+4404 -> 17980 | G44: 13733 | H44: =E44-F44+G44 -> 514793
